{
"meta":{"test_sets":[],"test_metrics":[],"learn_metrics":[{"best_value":"Min","name":"RMSE"}],"launch_mode":"Train","parameters":"","iteration_count":1000,"learn_sets":["learn"],"name":"experiment"},
"iterations":[
{"learn":[1.383167106],"iteration":0,"passed_time":0.04782218984,"remaining_time":47.77436765},
{"learn":[1.365380845],"iteration":1,"passed_time":0.05570108094,"remaining_time":27.79483939},
{"learn":[1.350029006],"iteration":2,"passed_time":0.06602423405,"remaining_time":21.94205378},
{"learn":[1.335495767],"iteration":3,"passed_time":0.07595516442,"remaining_time":18.91283594},
{"learn":[1.319398646],"iteration":4,"passed_time":0.08238516742,"remaining_time":16.39464832},
{"learn":[1.30501696],"iteration":5,"passed_time":0.086560596,"remaining_time":14.3402054},
{"learn":[1.291704748],"iteration":6,"passed_time":0.09493861828,"remaining_time":13.46772114},
{"learn":[1.279106886],"iteration":7,"passed_time":0.09999542145,"remaining_time":12.39943226},
{"learn":[1.264402274],"iteration":8,"passed_time":0.111449504,"remaining_time":12.27182872},
{"learn":[1.252105536],"iteration":9,"passed_time":0.1171956056,"remaining_time":11.60236496},
{"learn":[1.240868357],"iteration":10,"passed_time":0.1279569725,"remaining_time":11.50449507},
{"learn":[1.231323278],"iteration":11,"passed_time":0.1397255271,"remaining_time":11.5040684},
{"learn":[1.220560963],"iteration":12,"passed_time":0.1440725183,"remaining_time":10.93842889},
{"learn":[1.209928892],"iteration":13,"passed_time":0.1480536375,"remaining_time":10.42720618},
{"learn":[1.199532185],"iteration":14,"passed_time":0.1559473147,"remaining_time":10.24054033},
{"learn":[1.187560133],"iteration":15,"passed_time":0.1609061456,"remaining_time":9.895727952},
{"learn":[1.177307098],"iteration":16,"passed_time":0.1703205014,"remaining_time":9.848532521},
{"learn":[1.167136875],"iteration":17,"passed_time":0.1783113422,"remaining_time":9.727874334},
{"learn":[1.159615666],"iteration":18,"passed_time":0.190837289,"remaining_time":9.853230554},
{"learn":[1.154189547],"iteration":19,"passed_time":0.1969110401,"remaining_time":9.648640964},
{"learn":[1.14831432],"iteration":20,"passed_time":0.2032759934,"remaining_time":9.476533215},
{"learn":[1.136200571],"iteration":21,"passed_time":0.2106268474,"remaining_time":9.36332076},
{"learn":[1.1272552],"iteration":22,"passed_time":0.2203233912,"remaining_time":9.358954489},
{"learn":[1.121337876],"iteration":23,"passed_time":0.2274904629,"remaining_time":9.251278825},
{"learn":[1.112480497],"iteration":24,"passed_time":0.2430352493,"remaining_time":9.478374723},
{"learn":[1.106791301],"iteration":25,"passed_time":0.2506276632,"remaining_time":9.388897845},
{"learn":[1.098700488],"iteration":26,"passed_time":0.2583777156,"remaining_time":9.311167308},
{"learn":[1.091060694],"iteration":27,"passed_time":0.2647056442,"remaining_time":9.189067364},
{"learn":[1.08224264],"iteration":28,"passed_time":0.2706271378,"remaining_time":9.061343131},
{"learn":[1.076674532],"iteration":29,"passed_time":0.2757790611,"remaining_time":8.91685631},
{"learn":[1.069852],"iteration":30,"passed_time":0.2827918827,"remaining_time":8.839526913},
{"learn":[1.063087324],"iteration":31,"passed_time":0.2919991319,"remaining_time":8.832973739},
{"learn":[1.057327613],"iteration":32,"passed_time":0.2992092388,"remaining_time":8.767737391},
{"learn":[1.050976137],"iteration":33,"passed_time":0.3038128828,"remaining_time":8.63186014},
{"learn":[1.046077201],"iteration":34,"passed_time":0.3113055832,"remaining_time":8.58313965},
{"learn":[1.041534508],"iteration":35,"passed_time":0.3208140746,"remaining_time":8.590687997},
{"learn":[1.037576978],"iteration":36,"passed_time":0.3291969024,"remaining_time":8.568016676},
{"learn":[1.031441957],"iteration":37,"passed_time":0.3371785354,"remaining_time":8.535940818},
{"learn":[1.028010964],"iteration":38,"passed_time":0.3457315174,"remaining_time":8.519179185},
{"learn":[1.022705638],"iteration":39,"passed_time":0.3535634474,"remaining_time":8.485522738},
{"learn":[1.017104503],"iteration":40,"passed_time":0.3629719,"remaining_time":8.490001271},
{"learn":[1.012952658],"iteration":41,"passed_time":0.4184851213,"remaining_time":9.545446338},
{"learn":[1.007252564],"iteration":42,"passed_time":0.4278571498,"remaining_time":9.522309125},
{"learn":[1.001457223],"iteration":43,"passed_time":0.4359408957,"remaining_time":9.471806733},
{"learn":[0.9963885694],"iteration":44,"passed_time":0.4486428346,"remaining_time":9.521197935},
{"learn":[0.9921479547],"iteration":45,"passed_time":0.4568531677,"remaining_time":9.474737434},
{"learn":[0.9873963321],"iteration":46,"passed_time":0.4628245103,"remaining_time":9.384505497},
{"learn":[0.9836627197],"iteration":47,"passed_time":0.4676361118,"remaining_time":9.274782883},
{"learn":[0.9797070828],"iteration":48,"passed_time":0.4758607037,"remaining_time":9.23558223},
{"learn":[0.9746261601],"iteration":49,"passed_time":0.4809678956,"remaining_time":9.138390016},
{"learn":[0.9701490608],"iteration":50,"passed_time":0.4889579805,"remaining_time":9.098453402},
{"learn":[0.9660311389],"iteration":51,"passed_time":0.4963780264,"remaining_time":9.04935325},
{"learn":[0.9600521759],"iteration":52,"passed_time":0.5065522559,"remaining_time":9.051037477},
{"learn":[0.9558974248],"iteration":53,"passed_time":0.5159007603,"remaining_time":9.037817023},
{"learn":[0.9512063769],"iteration":54,"passed_time":0.5220689025,"remaining_time":8.970092961},
{"learn":[0.9475298471],"iteration":55,"passed_time":0.5363465261,"remaining_time":9.041270011},
{"learn":[0.9449190107],"iteration":56,"passed_time":0.5423421694,"remaining_time":8.972432732},
{"learn":[0.9410285104],"iteration":57,"passed_time":0.5539328011,"remaining_time":8.996632735},
{"learn":[0.936278686],"iteration":58,"passed_time":0.5643443063,"remaining_time":9.000813428},
{"learn":[0.9311342561],"iteration":59,"passed_time":0.5701463605,"remaining_time":8.932292981},
{"learn":[0.9290431246],"iteration":60,"passed_time":0.5738979326,"remaining_time":8.834264896},
{"learn":[0.9272565599],"iteration":61,"passed_time":0.5778325534,"remaining_time":8.74204734},
{"learn":[0.9237603886],"iteration":62,"passed_time":0.5856105499,"remaining_time":8.709795004},
{"learn":[0.9209857776],"iteration":63,"passed_time":0.5907746912,"remaining_time":8.640079859},
{"learn":[0.917542085],"iteration":64,"passed_time":0.6003523729,"remaining_time":8.635837979},
{"learn":[0.9142798314],"iteration":65,"passed_time":0.6068729209,"remaining_time":8.588171335},
{"learn":[0.9118506629],"iteration":66,"passed_time":0.616040936,"remaining_time":8.578599899},
{"learn":[0.9090946914],"iteration":67,"passed_time":0.6208307091,"remaining_time":8.50903266},
{"learn":[0.9070726019],"iteration":68,"passed_time":0.6258354406,"remaining_time":8.444243409},
{"learn":[0.9017129878],"iteration":69,"passed_time":0.6329096989,"remaining_time":8.408657428},
{"learn":[0.8995005297],"iteration":70,"passed_time":0.6392196507,"remaining_time":8.363874022},
{"learn":[0.8966581786],"iteration":71,"passed_time":0.6465808077,"remaining_time":8.333708188},
{"learn":[0.8936255191],"iteration":72,"passed_time":0.6528143352,"remaining_time":8.289847791},
{"learn":[0.8910054109],"iteration":73,"passed_time":0.6577070158,"remaining_time":8.230225631},
{"learn":[0.8873726673],"iteration":74,"passed_time":0.6633574557,"remaining_time":8.18140862},
{"learn":[0.8843772148],"iteration":75,"passed_time":0.6686797759,"remaining_time":8.129738328},
{"learn":[0.8820216404],"iteration":76,"passed_time":0.6734655085,"remaining_time":8.072839797},
{"learn":[0.8791285733],"iteration":77,"passed_time":0.6803905042,"remaining_time":8.042564678},
{"learn":[0.8775682773],"iteration":78,"passed_time":0.6847921852,"remaining_time":7.983463324},
{"learn":[0.875226392],"iteration":79,"passed_time":0.6887384688,"remaining_time":7.920492391},
{"learn":[0.8717741658],"iteration":80,"passed_time":0.6955269046,"remaining_time":7.891225004},
{"learn":[0.8693898111],"iteration":81,"passed_time":0.7005943167,"remaining_time":7.843238813},
{"learn":[0.8675486817],"iteration":82,"passed_time":0.7099145464,"remaining_time":7.843272759},
{"learn":[0.8645374033],"iteration":83,"passed_time":0.7143413127,"remaining_time":7.789721934},
{"learn":[0.8613725534],"iteration":84,"passed_time":0.7196587123,"remaining_time":7.746914373},
{"learn":[0.8576126543],"iteration":85,"passed_time":0.7276515123,"remaining_time":7.733412584},
{"learn":[0.8559404379],"iteration":86,"passed_time":0.7325979431,"remaining_time":7.68806807},
{"learn":[0.8548581083],"iteration":87,"passed_time":0.7419089943,"remaining_time":7.688875032},
{"learn":[0.8530814383],"iteration":88,"passed_time":0.7486067584,"remaining_time":7.662705134},
{"learn":[0.8512341133],"iteration":89,"passed_time":0.7580138909,"remaining_time":7.664362674},
{"learn":[0.8487406207],"iteration":90,"passed_time":0.7647970997,"remaining_time":7.639566633},
{"learn":[0.8470118366],"iteration":91,"passed_time":0.7725519349,"remaining_time":7.624751705},
{"learn":[0.8454078399],"iteration":92,"passed_time":0.7814878596,"remaining_time":7.621607405},
{"learn":[0.8430077174],"iteration":93,"passed_time":0.7906717003,"remaining_time":7.620729367},
{"learn":[0.840827235],"iteration":94,"passed_time":0.7983919646,"remaining_time":7.605733979},
{"learn":[0.8385507188],"iteration":95,"passed_time":0.8071067859,"remaining_time":7.600255567},
{"learn":[0.8356107051],"iteration":96,"passed_time":0.8171459069,"remaining_time":7.6070387},
{"learn":[0.8332910472],"iteration":97,"passed_time":0.8265679447,"remaining_time":7.607798838},
{"learn":[0.8309332196],"iteration":98,"passed_time":0.8325410943,"remaining_time":7.576964909},
{"learn":[0.82941814],"iteration":99,"passed_time":0.8401385808,"remaining_time":7.561247227},
{"learn":[0.826716072],"iteration":100,"passed_time":0.8469555638,"remaining_time":7.538743088},
{"learn":[0.8255103387],"iteration":101,"passed_time":0.8547890068,"remaining_time":7.525495374},
{"learn":[0.8246672923],"iteration":102,"passed_time":0.8615720212,"remaining_time":7.503204883},
{"learn":[0.8237756264],"iteration":103,"passed_time":0.8727298544,"remaining_time":7.518903361},
{"learn":[0.8223335563],"iteration":104,"passed_time":0.8819190233,"remaining_time":7.51730977},
{"learn":[0.8188403688],"iteration":105,"passed_time":0.8905564955,"remaining_time":7.510919877},
{"learn":[0.8178470328],"iteration":106,"passed_time":0.8959537829,"remaining_time":7.477446057},
{"learn":[0.816145959],"iteration":107,"passed_time":0.9017773045,"remaining_time":7.448012552},
{"learn":[0.8147741713],"iteration":108,"passed_time":0.9061799734,"remaining_time":7.407397764},
{"learn":[0.8124716746],"iteration":109,"passed_time":0.9112287466,"remaining_time":7.372668949},
{"learn":[0.8102105728],"iteration":110,"passed_time":0.9179437105,"remaining_time":7.351819447},
{"learn":[0.8085465165],"iteration":111,"passed_time":0.9221216898,"remaining_time":7.311107684},
{"learn":[0.805994643],"iteration":112,"passed_time":0.9272653095,"remaining_time":7.278622385},
{"learn":[0.8047025482],"iteration":113,"passed_time":0.9325967198,"remaining_time":7.248076261},
{"learn":[0.802557841],"iteration":114,"passed_time":0.9373134463,"remaining_time":7.213238261},
{"learn":[0.8004136835],"iteration":115,"passed_time":0.9461055018,"remaining_time":7.209976411},
{"learn":[0.7986030561],"iteration":116,"passed_time":0.9526880323,"remaining_time":7.189944723},
{"learn":[0.7963029912],"iteration":117,"passed_time":0.9575992709,"remaining_time":7.157648788},
{"learn":[0.7943377159],"iteration":118,"passed_time":0.9646066887,"remaining_time":7.141331872},
{"learn":[0.7927082367],"iteration":119,"passed_time":0.9701129411,"remaining_time":7.114161568},
{"learn":[0.7906998611],"iteration":120,"passed_time":0.9954352631,"remaining_time":7.231302448},
{"learn":[0.7893650342],"iteration":121,"passed_time":1.012883131,"remaining_time":7.289437617},
{"learn":[0.7879424331],"iteration":122,"passed_time":1.031617271,"remaining_time":7.355515013},
{"learn":[0.7861375832],"iteration":123,"passed_time":1.051522451,"remaining_time":7.428497312},
{"learn":[0.7851176646],"iteration":124,"passed_time":1.057930584,"remaining_time":7.405514088},
{"learn":[0.7829566641],"iteration":125,"passed_time":1.07214769,"remaining_time":7.436960962},
{"learn":[0.7816653178],"iteration":126,"passed_time":1.087502041,"remaining_time":7.475506155},
{"learn":[0.7801399508],"iteration":127,"passed_time":1.09206168,"remaining_time":7.439670198},
{"learn":[0.7786165134],"iteration":128,"passed_time":1.100318518,"remaining_time":7.429282396},
{"learn":[0.7744215252],"iteration":129,"passed_time":1.105591972,"remaining_time":7.398961656},
{"learn":[0.7731608583],"iteration":130,"passed_time":1.110290342,"remaining_time":7.365208454},
{"learn":[0.7719456838],"iteration":131,"passed_time":1.1253551,"remaining_time":7.400062327},
{"learn":[0.7695566767],"iteration":132,"passed_time":1.139870387,"remaining_time":7.43058365},
{"learn":[0.7680177733],"iteration":133,"passed_time":1.153860598,"remaining_time":7.457039386},
{"learn":[0.7658344368],"iteration":134,"passed_time":1.173636658,"remaining_time":7.519968214},
{"learn":[0.7647241503],"iteration":135,"passed_time":1.189170244,"remaining_time":7.554728607},
{"learn":[0.762983426],"iteration":136,"passed_time":1.201850688,"remaining_time":7.570782068},
{"learn":[0.75975121],"iteration":137,"passed_time":1.21949534,"remaining_time":7.617427416},
{"learn":[0.7564076784],"iteration":138,"passed_time":1.22709706,"remaining_time":7.600939342},
{"learn":[0.7544174367],"iteration":139,"passed_time":1.236499559,"remaining_time":7.59564015},
{"learn":[0.7520610385],"iteration":140,"passed_time":1.250670743,"remaining_time":7.619334524},
{"learn":[0.750641652],"iteration":141,"passed_time":1.258108614,"remaining_time":7.601811203},
{"learn":[0.74947115],"iteration":142,"passed_time":1.265541167,"remaining_time":7.584397066},
{"learn":[0.7474979711],"iteration":143,"passed_time":1.269703464,"remaining_time":7.547681705},
{"learn":[0.7458941428],"iteration":144,"passed_time":1.276734351,"remaining_time":7.528330138},
{"learn":[0.7445780536],"iteration":145,"passed_time":1.282706616,"remaining_time":7.502955139},
{"learn":[0,
{"learn":[0.7453458222],"iteration":146,"passed_time":1.419989844,"remaining_time",
{"learn":[0,
{"learn":[0.7435893076],"iteration":147,"passed_time":1.430938108,"remaining_time":8.237562624},
{"learn":[0.7421772347],"iteration":148,"passed_time":1.440410256,"remaining_time":8.226772669},
{"learn":[0.7403343499],"iteration":149,"passed_time":1.455268602,"remaining_time":8.246522077},
{"learn":[0.7388492906],"iteration":150,"passed_time":1.478863323,"remaining_time":8.314933518},
{"learn":[0.7374971297],"iteration":151,"passed_time":1.493335663,"remaining_time":8.331241065},
{"learn":[0.7353134293],"iteration":152,"passed_time":1.510130175,"remaining_time":8.360001689},
{"learn":[0.7340547898],"iteration":153,"passed_time":1.516133529,"remaining_time":8.328889389},
{"learn":[0.7314339975],"iteration":154,"passed_time":1.529513548,"remaining_time":8.338315792},
{"learn":[0.729429818],"iteration":155,"passed_time":1.557960812,"remaining_time":8.428967471},
{"learn":[0.7274252107],"iteration":156,"passed_time":1.578008132,"remaining_time":8.47299908},
{"learn":[0.7258484289],"iteration":157,"passed_time":1.600018535,"remaining_time":8.526681051},
{"learn":[0.7244156241],"iteration":158,"passed_time":1.629785846,"remaining_time":8.6204396},
{"learn":[0.7235915614],"iteration":159,"passed_time":1.640681816,"remaining_time":8.613579532},
{"learn":[0.7224805947],"iteration":160,"passed_time":1.651831792,"remaining_time":8.607993003},
{"learn":[0.7204437681],"iteration":161,"passed_time":1.663022345,"remaining_time":8.602547683},
{"learn":[0.7192978005],"iteration":162,"passed_time":1.671857305,"remaining_time":8.584935979},
{"learn":[0.7173986234],"iteration":163,"passed_time":1.686990195,"remaining_time":8.599535383},
{"learn":[0.716873777],"iteration":164,"passed_time":1.698109368,"remaining_time":8.59346256},
{"learn":[0.7161417712],"iteration":165,"passed_time":1.709063693,"remaining_time":8.586500724},
{"learn":[0.714033265],"iteration":166,"passed_time":1.716720564,"remaining_time":8.563043291},
{"learn":[0.712926203],"iteration":167,"passed_time":1.734814775,"remaining_time":8.59146365},
{"learn":[0.7114581186],"iteration":168,"passed_time":1.750951223,"remaining_time":8.609706903},
{"learn":[0.7102495859],"iteration":169,"passed_time":1.763321238,"remaining_time":8.609156631},
{"learn":[0.7089093007],"iteration":170,"passed_time":1.77271015,"remaining_time":8.594015874},
{"learn":[0.7067270683],"iteration":171,"passed_time":1.779849477,"remaining_time":8.5681126},
{"learn":[0.705560142],"iteration":172,"passed_time":1.790006326,"remaining_time":8.55685105},
{"learn":[0.7031726885],"iteration":173,"passed_time":1.798318567,"remaining_time":8.536845612},
{"learn":[0.7015589421],"iteration":174,"passed_time":1.808888587,"remaining_time":8.527617626},
{"learn":[0.69997067],"iteration":175,"passed_time":1.817540736,"remaining_time":8.509395262},
{"learn":[0.6986403076],"iteration":176,"passed_time":1.836034722,"remaining_time":8.537042802},
{"learn":[0.6969550775],"iteration":177,"passed_time":1.842764454,"remaining_time":8.509844838},
{"learn":[0.6956040259],"iteration":178,"passed_time":1.854937177,"remaining_time":8.507840349},
{"learn":[0.694449886],"iteration":179,"passed_time":1.867371879,"remaining_time":8.506916335},
{"learn":[0.6939496508],"iteration":180,"passed_time":1.882895565,"remaining_time":8.519842364},
{"learn":[0.6924760902],"iteration":181,"passed_time":1.893034559,"remaining_time":8.508254226},
{"learn":[0.6915874241],"iteration":182,"passed_time":1.90039971,"remaining_time":8.48429816},
{"learn":[0.6906850798],"iteration":183,"passed_time":1.904152169,"remaining_time":8.444500925},
{"learn":[0.689950774],"iteration":184,"passed_time":1.911467181,"remaining_time":8.420787851},
{"learn":[0.688932015],"iteration":185,"passed_time":1.916457005,"remaining_time":8.387075279},
{"learn":[0.6877746186],"iteration":186,"passed_time":1.920319936,"remaining_time":8.348770631},
{"learn":[0.6868754286],"iteration":187,"passed_time":1.927107749,"remaining_time":8.323465386},
{"learn":[0.6862028846],"iteration":188,"passed_time":1.93220012,"remaining_time":8.291080937},
{"learn":[0.6850289208],"iteration":189,"passed_time":1.941166241,"remaining_time":8.275498184},
{"learn":[0.6836413657],"iteration":190,"passed_time":1.946482428,"remaining_time":8.24452505},
{"learn":[0.6825037878],"iteration":191,"passed_time":1.953736517,"remaining_time":8.221974509},
{"learn":[0.6809442026],"iteration":192,"passed_time":1.96112409,"remaining_time":8.200140624},
{"learn":[0.6798140843],"iteration":193,"passed_time":1.967022015,"remaining_time":8.172266721},
{"learn":[0.6779211325],"iteration":194,"passed_time":1.972134013,"remaining_time":8.141373746},
{"learn":[0.6770337175],"iteration":195,"passed_time":1.977217506,"remaining_time":8.110626913},
{"learn":[0.6753471795],"iteration":196,"passed_time":1.981381178,"remaining_time":8.076391298},
{"learn":[0.6738092749],"iteration":197,"passed_time":1.985533079,"remaining_time":8.042411763},
{"learn":[0.6728829272],"iteration":198,"passed_time":1.991088754,"remaining_time":8.014382373},
{"learn":[0.6699285096],"iteration":199,"passed_time":1.996504822,"remaining_time":7.98601929},
{"learn":[0.6682900414],"iteration":200,"passed_time":2.001163727,"remaining_time":7.954874714},
{"learn":[0.6673132043],"iteration":201,"passed_time":2.009975011,"remaining_time":7.940396333},
{"learn":[0.6650315849],"iteration":202,"passed_time":2.019807918,"remaining_time":7.929984783},
{"learn":[0.6638492547],"iteration":203,"passed_time":2.031614044,"remaining_time":7.927278328},
{"learn":[0.6625310435],"iteration":204,"passed_time":2.043372832,"remaining_time":7.92429952},
{"learn":[0.6604736755],"iteration":205,"passed_time":2.047935727,"remaining_time":7.893499842},
{"learn":[0.6600352529],"iteration":206,"passed_time":2.05647861,"remaining_time":7.878200665},
{"learn":[0.6587619066],"iteration":207,"passed_time":2.064493577,"remaining_time":7.860956312},
{"learn":[0.6573510956],"iteration":208,"passed_time":2.074388398,"remaining_time":7.850914943},
{"learn":[0.6557668374],"iteration":209,"passed_time":2.083201683,"remaining_time":7.83680633},
{"learn":[0.6551842034],"iteration":210,"passed_time":2.089470461,"remaining_time":7.813233144},
{"learn":[0.654304079],"iteration":211,"passed_time":2.094435922,"remaining_time":7.784978803},
{"learn":[0.6521229446],"iteration":212,"passed_time":2.10671887,"remaining_time":7.783980051},
{"learn":[0.6513749333],"iteration":213,"passed_time":2.112314629,"remaining_time":7.758314479},
{"learn":[0.6506784569],"iteration":214,"passed_time":2.119188665,"remaining_time":7.737502801},
{"learn":[0.6490464967],"iteration":215,"passed_time":2.123479633,"remaining_time":7.707444592},
{"learn":[0.648153265],"iteration":216,"passed_time":2.128488917,"remaining_time":7.680215769},
{"learn":[0.6464247045],"iteration":217,"passed_time":2.13703373,"remaining_time":7.665873289},
{"learn":[0.645625195],"iteration":218,"passed_time":2.144969526,"remaining_time":7.64941187},
{"learn":[0.6453413821],"iteration":219,"passed_time":2.153313357,"remaining_time":7.634474629},
{"learn":[0.6445843618],"iteration":220,"passed_time":2.164359494,"remaining_time":7.62912238},
{"learn":[0.6438063331],"iteration":221,"passed_time":2.174499899,"remaining_time":7.620544693},
{"learn":[0.6428842757],"iteration":222,"passed_time":2.18268073,"remaining_time":7.605125235},
{"learn":[0.6409108162],"iteration":223,"passed_time":2.199156198,"remaining_time":7.618505399},
{"learn":[0.6402915116],"iteration":224,"passed_time":2.213309812,"remaining_time":7.623622686},
{"learn":[0.639162574],"iteration":225,"passed_time":2.224315445,"remaining_time":7.617788294},
{"learn":[0.6375744092],"iteration":226,"passed_time":2.23116346,"remaining_time":7.59775046},
{"learn":[0.6365915201],"iteration":227,"passed_time":2.23810541,"remaining_time":7.578146388},
{"learn":[0.6351698266],"iteration":228,"passed_time":2.252300552,"remaining_time":7.583073037},
{"learn":[0.633781286],"iteration":229,"passed_time":2.262880364,"remaining_time":7.575729914},
{"learn":[0.6326884426],"iteration":230,"passed_time":2.269095063,"remaining_time":7.553827288},
{"learn":[0.6315229403],"iteration":231,"passed_time":2.279153629,"remaining_time":7.544784426},
{"learn":[0.6308012261],"iteration":232,"passed_time":2.287438609,"remaining_time":7.529894478},
{"learn":[0.629485521],"iteration":233,"passed_time":2.299011944,"remaining_time":7.525825424},
{"learn":[0.6287938666],"iteration":234,"passed_time":2.312371364,"remaining_time":7.527506781},
{"learn":[0.6282689379],"iteration":235,"passed_time":2.3229329,"remaining_time":7.520003116},
{"learn":[0.6266825833],"iteration":236,"passed_time":2.33443529,"remaining_time":7.515502643},
{"learn":[0.6261601974],"iteration":237,"passed_time":2.348166502,"remaining_time":7.518079304},
{"learn":[0.6250783684],"iteration":238,"passed_time":2.364236963,"remaining_time":7.527967902},
{"learn":[0.6243772602],"iteration":239,"passed_time":2.376647455,"remaining_time":7.526050274},
{"learn":[0.6228380227],"iteration":240,"passed_time":2.38191313,"remaining_time":7.50154384},
{"learn":[0.6220059076],"iteration":241,"passed_time":2.393031957,"remaining_time":7.495529849},
{"learn":[0.6209403336],"iteration":242,"passed_time":2.401880408,"remaining_time":7.482401105},
{"learn":[0.6197565492],"iteration":243,"passed_time":2.408978144,"remaining_time":7.463883103},
{"learn":[0.6188143133],"iteration":244,"passed_time":2.419637275,"remaining_time":7.456433237},
{"learn":[0.6172012722],"iteration":245,"passed_time":2.429310839,"remaining_time":7.445936474},
{"learn":[0.6163056867],"iteration":246,"passed_time":2.440898189,"remaining_time":7.441280713},
{"learn":[0.615074277],"iteration":247,"passed_time":2.454242612,"remaining_time":7.441896953},
{"learn":[0.614270233],"iteration":248,"passed_time":2.46411638,"remaining_time":7.431933339},
{"learn":[0.612971643],"iteration":249,"passed_time":2.476107768,"remaining_time":7.428323304},
{"learn":[0.6118290321],"iteration":250,"passed_time":2.486565199,"remaining_time":7.420069059},
{"learn":[0.6101564628],"iteration":251,"passed_time":2.494106713,"remaining_time":7.403142149},
{"learn":[0.6096058908],"iteration":252,"passed_time":2.503793416,"remaining_time":7.392623247},
{"learn":[0.6089191672],"iteration":253,"passed_time":2.514961253,"remaining_time":7.386461003},
{"learn":[0.6076620214],"iteration":254,"passed_time":2.524587425,"remaining_time":7.375755417},
{"learn":[0.6071322929],"iteration":255,"passed_time":2.533011902,"remaining_time":7.361565841},
{"learn":[0.6067770642],"iteration":256,"passed_time":2.539192591,"remaining_time":7.340934222},
{"learn":[0.6057843819],"iteration":257,"passed_time":2.547332428,"remaining_time":7.326049076},
{"learn":[0.6047197413],"iteration":258,"passed_time":2.572627126,"remaining_time":7.360296142},
{"learn":[0.6036384223],"iteration":259,"passed_time":2.591815299,"remaining_time":7.376705081},
{"learn":[0.6031585558],"iteration":260,"passed_time":2.615785291,"remaining_time":7.406380576},
{"learn":[0.6021387997],"iteration":261,"passed_time":2.62126172,"remaining_time":7.383554005},
{"learn":[0.600632908],"iteration":262,"passed_time":2.627940593,"remaining_time":7.364228961},
{"learn":[0.5996322185],"iteration":263,"passed_time":2.633419599,"remaining_time":7.341654638},
{"learn":[0.5993523105],"iteration":264,"passed_time":2.640463301,"remaining_time":7.323549155},
{"learn":[0.5981389699],"iteration":265,"passed_time":2.651959166,"remaining_time":7.317812133},
{"learn":[0.5973330211],"iteration":266,"passed_time":2.663870478,"remaining_time":7.313172511},
{"learn":[0.5966245248],"iteration":267,"passed_time":2.676869219,"remaining_time":7.311448763},
{"learn":[0.5957794625],"iteration":268,"passed_time":2.682050744,"remaining_time":7.288398118},
{"learn":[0.594980533],"iteration":269,"passed_time":2.687538505,"remaining_time":7.266307809},
{"learn":[0.5934914043],"iteration":270,"passed_time":2.693660335,"remaining_time":7.246045697},
{"learn":[0.5931984182],"iteration":271,"passed_time":2.698123806,"remaining_time":7.221449011},
{"learn":[0.5923754451],"iteration":272,"passed_time":2.710834223,"remaining_time":7.218961465},
{"learn":[0.59200883],"iteration":273,"passed_time":2.723784061,"remaining_time":7.217033679},
{"learn":[0.5912954754],"iteration":274,"passed_time":2.730935929,"remaining_time":7.199740178},
{"learn":[0.5896852103],"iteration":275,"passed_time":2.738725002,"remaining_time":7.184191671},
{"learn":[0.588834079],"iteration":276,"passed_time":2.744705255,"remaining_time":7.163977975},
{"learn":[0.5881168758],"iteration":277,"passed_time":2.752622133,"remaining_time":7.148896332},
{"learn":[0.5869082928],"iteration":278,"passed_time":2.759443659,"remaining_time":7.131035406},
{"learn":[0.5862095166],"iteration":279,"passed_time":2.774390237,"remaining_time":7.134146323},
{"learn":[0.5855449455],"iteration":280,"passed_time":2.787437165,"remaining_time":7.132268048},
{"learn":[0.5849048596],"iteration":281,"passed_time":2.796284252,"remaining_time":7.119617352},
{"learn":[0.5844320547],"iteration":282,"passed_time":2.803004448,"remaining_time":7.10160491},
{"learn":[0.5841587652],"iteration":283,"passed_time":2.809556441,"remaining_time":7.083247928},
{"learn":[0.5835022656],"iteration":284,"passed_time":2.817659263,"remaining_time":7.068864466},
{"learn":[0.5825811852],"iteration":285,"passed_time":2.822647526,"remaining_time":7.046749419},
{"learn":[0.5810638053],"iteration":286,"passed_time":2.827181939,"remaining_time":7.023626211},
{"learn":[0.5809962149],"iteration":287,"passed_time":2.833609868,"remaining_time":7.005313286},
{"learn":[0.5801478666],"iteration":288,"passed_time":2.853214569,"remaining_time":7.019500202},
{"learn":[0.5795841785],"iteration":289,"passed_time":2.865143459,"remaining_time":7.014661572},
{"learn":[0.5789605501],"iteration":290,"passed_time":2.871715944,"remaining_time":6.996723727},
{"learn":[0.578617763],"iteration":291,"passed_time":2.876673839,"remaining_time":6.974948898},
{"learn":[0.5782376707],"iteration":292,"passed_time":2.882739718,"remaining_time":6.955962392},
{"learn":[0.5774742107],"iteration":293,"passed_time":2.887700495,"remaining_time":6.934410032},
{"learn":[0.5768005024],"iteration":294,"passed_time":2.895385644,"remaining_time":6.919480945},
{"learn":[0.5762093031],"iteration":295,"passed_time":2.905451613,"remaining_time":6.910263296},
{"learn":[0.5750931603],"iteration":296,"passed_time":2.925212377,"remaining_time":6.923987545},
{"learn":[0.5745870774],"iteration":297,"passed_time":2.932477752,"remaining_time":6.908051616},
{"learn":[0.5738849355],"iteration":298,"passed_time":2.938020292,"remaining_time":6.88813453},
{"learn":[0.5727189301],"iteration":299,"passed_time":2.945964243,"remaining_time":6.873916567},
{"learn":[0.5718720701],"iteration":300,"passed_time":2.950682406,"remaining_time":6.852249176},
{"learn":[0.5710650122],"iteration":301,"passed_time":2.958416659,"remaining_time":6.837664993},
{"learn":[0.5703393535],"iteration":302,"passed_time":2.965115257,"remaining_time":6.820743676},
{"learn":[0.5696943774],"iteration":303,"passed_time":2.969456248,"remaining_time":6.798491936},
{"learn":[0.5690631173],"iteration":304,"passed_time":2.976710278,"remaining_time":6.782995553},
{"learn":[0.5677642171],"iteration":305,"passed_time":2.982296019,"remaining_time":6.763769403},
{"learn":[0.5670325622],"iteration":306,"passed_time":2.990157327,"remaining_time":6.749768819},
{"learn":[0.5657550736],"iteration":307,"passed_time":2.999878869,"remaining_time":6.739987589},
{"learn":[0.5654681749],"iteration":308,"passed_time":3.009308486,"remaining_time":6.729553929},
{"learn":[0.5645719685],"iteration":309,"passed_time":3.017854004,"remaining_time":6.717158913},
{"learn":[0.5643011405],"iteration":310,"passed_time":3.024584435,"remaining_time":6.700767445},
{"learn":[0.5635238776],"iteration":311,"passed_time":3.028530882,"remaining_time":6.678298869},
{"learn":[0.5626374916],"iteration":312,"passed_time":3.035235974,"remaining_time":,
{"learn":[0.5610989841],"iteration":313,"passed_time":2.918433197,"remaining_time":6.375940043},
{"learn":[0.5597555046],"iteration":314,"passed_time":2.933688818,"remaining_time":6.379609018},
{"learn":[0.5583816106],"iteration":315,"passed_time":2.943528813,"remaining_time":6.371435785},
{"learn":[0.558106539],"iteration":316,"passed_time":2.957777927,"remaining_time":6.372751811},
{"learn":[0.5567778894],"iteration":317,"passed_time":2.96863487,"remaining_time":6.36669491},
{"learn":[0.5559452693],"iteration":318,"passed_time":2.979151348,"remaining_time":6.35988109},
{"learn":[0.555679624],"iteration":319,"passed_time":2.987942374,"remaining_time":6.349377546},
{"learn":[0.554993993],"iteration":320,"passed_time":2.993927623,"remaining_time":6.332949707},
{"learn":[0.5544173388],"iteration":321,"passed_time":3.003298317,"remaining_time":6.323715091},
{"learn":[0.553218152],"iteration":322,"passed_time":3.010317945,"remaining_time":6.309551855},
{"learn":[0.5522395824],"iteration":323,"passed_time":3.05332577,"remaining_time":6.370519198},
{"learn":[0.5514089448],"iteration":324,"passed_time":3.061973339,"remaining_time":6.359483089},
{"learn":[0.5505023123],"iteration":325,"passed_time":3.07109324,"remaining_time":6.349438172},
{"learn":[0.5501574572],"iteration":326,"passed_time":3.077716403,"remaining_time":6.334260365},
{"learn":[0.5496124158],"iteration":327,"passed_time":3.084954848,"remaining_time":6.320395299},
{"learn":[0.5484389558],"iteration":328,"passed_time":3.125418162,"remaining_time":6.374333091},
{"learn":[0.5479204935],"iteration":329,"passed_time":3.145516706,"remaining_time":6.386352101},
{"learn":[0.5473276342],"iteration":330,"passed_time":3.153352291,"remaining_time":6.373391791},
{"learn":[0.5463478922],"iteration":331,"passed_time":3.167527091,"remaining_time":6.37321716},
{"learn":[0.5460603517],"iteration":332,"passed_time":3.178410571,"remaining_time":6.366365918},
{"learn":[0.5457673821],"iteration":333,"passed_time":3.200999588,"remaining_time":6.382831514},
{"learn":[0.544346161],"iteration":334,"passed_time":3.208608587,"remaining_time":6.369327493},
{"learn":[0.5433457711],"iteration":335,"passed_time":3.216666586,"remaining_time":6.356745872},
{"learn":[0.5420346184],"iteration":336,"passed_time":3.224940397,"remaining_time":6.344615678},
{"learn":[0.5411322476],"iteration":337,"passed_time":3.231885671,"remaining_time":6.329906255},
{"learn":[0.5401113634],"iteration":338,"passed_time":3.238626251,"remaining_time":6.314843517},
{"learn":[0.5390698265],"iteration":339,"passed_time":3.248829701,"remaining_time":6.306551773},
{"learn":[0.5382478043],"iteration":340,"passed_time":3.259812906,"remaining_time":6.299755733},
{"learn":[0.5379377022],"iteration":341,"passed_time":3.26768153,"remaining_time":6.286942827},
{"learn":[0.53,
{"learn":[0.5426865505],"iteration":342,"passed_time":3.401667232,"remaining_ti,
{"learn":[0.53,
{"learn":[0.5421598518],"iteration":343,"passed_time":3.415908012,"remaining_ti,
{"learn":[0.5,
{"learn":[0.5415144726],"iteration":344,"passed_time":3.429677501,"remaining_ti,
{"learn":[0.5355968066],"iteration":345,"passed_time":3.324473049,"remaining_time":6.28383056},
{"learn":[0.5350594287],"iteration":346,"passed_time":3.337204732,"remaining_time":6.28009997},
{"learn":[0.534787492],"iteration":347,"passed_time":3.341414639,"remaining_time":6.260351565},
{"learn":[0.5335384773],"iteration":348,"passed_time":3.348329804,"remaining_time":6.245738403},
{"learn":[0.5329,
{"learn":[0.5368607316],"iteration":349,"passed_time":3.489431433,"remaining_time":6.480372662},
{"learn":[0.536684467],"iteration":350,"passed_time":3.499575617,"remaining_time":6.470725286},
{"learn":[0.536236207],"iteration":351,"passed_time":3.512853315,"remaining_time":6.466843602},
{"learn":[0.5358369895],"iteration":352,"passed_time":3.529596211,"remaining_time":6.469259911},
{"learn":[0.5355085929],"iteration":353,"passed_time":3.541354701,"remaining_time":6.462472138},
{"learn":[0.5343267091],"iteration":354,"passed_time":3.549539979,"remaining_time":6.449164187},
{"learn":[0.5339700847],"iteration":355,"passed_time":3.566337242,"remaining_time":6.451463999},
{"learn":[0.5332917928],"iteration":356,"passed_time":3.579745389,"remaining_time":6.447552619},
{"learn":[0.5327411],"iteration":357,"passed_time":3.586426688,"remaining_time":6.431524955},
{"learn":[0.5322077685],"iteration":358,"passed_time":3.598352579,"remaining_time":6.424913657},
{"learn":[0.5309209442],"iteration":359,"passed_time":3.611193101,"remaining_time":6.419898846},
{"learn":[0.5299737559],"iteration":360,"passed_time":3.621224873,"remaining_time":6.409868958},
{"learn":[0.5292699153],"iteration":361,"passed_time":3.628786121,"remaining_time":6.395484931},
{"learn":[0.5285973291],"iteration":362,"passed_time":3.640655492,"remaining_time":6.38869848},
{"learn":[0.5274303235],"iteration":363,"passed_time":3.647469571,"remaining_time":6.373051228},
{"learn":[0.5261919275],"iteration":364,"passed_time":3.656195835,"remaining_time":6.360779056},
{"learn":[0.5260173882],"iteration":365,"passed_time":3.661953558,"remaining_time":6.343384032},
{"learn":[0.5249566081],"iteration":366,"passed_time":3.669591418,"remaining_time":6.32929528},
{"learn":[0.5248349951],"iteration":367,"passed_time":3.71031115,"remaining_time":6.372056105},
{"learn":[0.5245852848],"iteration":368,"passed_time":3.741647597,"remaining_time":6.39831879},
{"learn":[0.5238901717],"iteration":369,"passed_time":3.746327029,"remaining_time":6.378881158},
{"learn":[0.5228004342],"iteration":370,"passed_time":3.756465957,"remaining_time":6.368779209},
{"learn":[0.5225236986],"iteration":371,"passed_time":3.764151206,"remaining_time":6.354534832},
{"learn":[0.521765869],"iteration":372,"passed_time":3.772102268,"remaining_time":6.340772445},
{"learn":[0.520608578],"iteration":373,"passed_time":3.783407687,"remaining_time":6.332655648},
{"learn":[0.5192752539],"iteration":374,"passed_time":3.789661287,"remaining_time":6.316102145},
{"learn":[0.5180728847],"iteration":375,"passed_time":3.801051254,"remaining_time":6.308127614},
{"learn":[0.5173484942],"iteration":376,"passed_time":3.808162151,"remaining_time":6.293063714},
{"learn":[0.5166975278],"iteration":377,"passed_time":3.819119624,"remaining_time":6.284371445},
{"learn":[0.5161550926],"iteration":378,"passed_time":3.831454083,"remaining_time":6.277923445},
{"learn":[0.515983839],"iteration":379,"passed_time":3.83822979,"remaining_time":6.26237492},
{"learn":[0.5157675085],"iteration":380,"passed_time":3.845156094,"remaining_time":6.247117119},
{"learn":[0.5154453304],"iteration":381,"passed_time":3.854123011,"remaining_time":6.235204242},
{"learn":[0.515094605],"iteration":382,"passed_time":3.862376334,"remaining_time":6.222157176},
{"learn":[0.5140299986],"iteration":383,"passed_time":3.870454807,"remaining_time":6.208854587},
{"learn":[0.5134273235],"iteration":384,"passed_time":3.879218897,"remaining_time":6.196674342},
{"learn":[0.5128570363],"iteration":385,"passed_time":3.884992209,"remaining_time":6.179754447},
{"learn":[0.5117037536],"iteration":386,"passed_time":3.890236731,"remaining_time":6.162054564},
{"learn":[0.5112525122],"iteration":387,"passed_time":3.897369042,"remaining_time":6.14739653},
{"learn":[0.5109348488],"iteration":388,"passed_time":3.904414748,"remaining_time":6.13264116},
{"learn":[0.5103762488],"iteration":389,"passed_time":3.914895586,"remaining_time":6.123298224},
{"learn":[0.5094568379],"iteration":390,"passed_time":3.920391808,"remaining_time":6.106185707},
{"learn":[0.509018351],"iteration":391,"passed_time":3.929709887,"remaining_time":6.095060233},
{"learn":[0.5085507345],"iteration":392,"passed_time":3.939821228,"remaining_time":6.085169173},
{"learn":[0.5079650694],"iteration":393,"passed_time":3.954423816,"remaining_time":6.082184854},
{"learn":[0.5075479225],"iteration":394,"passed_time":3.964508975,"remaining_time":6.072222607},
{"learn":[0.5072599756],"iteration":395,"passed_time":3.969156231,"remaining_time":6.053965565},
{"learn":[0.5067515052],"iteration":396,"passed_time":3.980481743,"remaining_time":6.045920632},
{"learn":[0.5055079291],"iteration":397,"passed_time":3.990370664,"remaining_time":6.035686281},
{"learn":[0.5052556581],"iteration":398,"passed_time":3.999089683,"remaining_time":6.023691477},
{"learn":[0.5044528422],"iteration":399,"passed_time":4.007407319,"remaining_time":6.011110978},
{"learn":[0.5042840351],"iteration":400,"passed_time":4.014165146,"remaining_time":5.996221752},
{"learn":[0.502758713],"iteration":401,"passed_time":4.020069015,"remaining_time":5.980102664},
{"learn":[0.5019969394],"iteration":402,"passed_time":4.028998144,"remaining_time":5.96851586},
{"learn":[0.5013065015],"iteration":403,"passed_time":4.039842613,"remaining_time":5.959767815},
{"learn":[0.5005778465],"iteration":404,"passed_time":4.045891646,"remaining_time":5.943964271},
{"learn":[0.4998002235],"iteration":405,"passed_time":4.053737372,"remaining_time":5.930837436},
{"learn":[0.4986698505],"iteration":406,"passed_time":4.061024292,"remaining_time":5.916922371},
{"learn":[0.4974727261],"iteration":407,"passed_time":4.069674385,"remaining_time":5.905017735},
{"learn":[0.4972911326],"iteration":408,"passed_time":4.078020122,"remaining_time":5.892689222},
{"learn":[0.4968510082],"iteration":409,"passed_time":4.084860303,"remaining_time":5.878213607},
{"learn":[0.4965821622],"iteration":410,"passed_time":4.092686453,"remaining_time":5.865188128},
{"learn":[0.4959808114],"iteration":411,"passed_time":4.101338894,"remaining_time":5.85336716},
{"learn":[0.4956129547],"iteration":412,"passed_time":4.10743479,"remaining_time":5.837927898},
{"learn":[0.4951325475],"iteration":413,"passed_time":4.116340644,"remaining_time":5.826511153},
{"learn":[0.4951022197],"iteration":414,"passed_time":4.124736473,"remaining_time":5.814387559},
{"learn":[0.4948767662],"iteration":415,"passed_time":4.134340489,"remaining_time":5.803977995},
{"learn":[0.4947756884],"iteration":416,"passed_time":4.139834463,"remaining_time":5.78782612},
{"learn":[0.4942353042],"iteration":417,"passed_time":4.14570341,"remaining_time":5.772247332},
{"learn":[0.4937935763],"iteration":418,"passed_time":4.152398864,"remaining_time":5.757860955},
{"learn":[0.4935370846],"iteration":419,"passed_time":4.158687637,"remaining_time":5.742949593},
{"learn":[0.4930563595],"iteration":420,"passed_time":4.165690339,"remaining_time":5.72906106},
{"learn":[0.4924599818],"iteration":421,"passed_time":4.172976505,"remaining_time":5.715593412},
{"learn":[0.491916576],"iteration":422,"passed_time":4.181590959,"remaining_time":5.703966864},
{"learn":[0.4917346228],"iteration":423,"passed_time":4.189177993,"remaining_time":5.690958782},
{"learn":[0.4910013712],"iteration":424,"passed_time":4.198759851,"remaining_time":5.680675092},
{"learn":[0.4906386697],"iteration":425,"passed_time":4.205185435,"remaining_time":5.666141878},
{"learn":[0.4898533203],"iteration":426,"passed_time":4.213304453,"remaining_time":5.65391909},
{"learn":[0.4898259629],"iteration":427,"passed_time":4.223468028,"remaining_time":5.644447926},
{"learn":[0.4894861494],"iteration":428,"passed_time":4.233497959,"remaining_time":5.634795652},
{"learn":[0.4886936278],"iteration":429,"passed_time":4.253056009,"remaining_time":5.637771919},
{"learn":[0.4879954802],"iteration":430,"passed_time":4.263891714,"remaining_time":5.629128504},
{"learn":[0.4878194622],"iteration":431,"passed_time":4.269270011,"remaining_time":5.613299459},
{"learn":[0.4873719],"iteration":432,"passed_time":4.276268408,"remaining_time":5.599640156},
{"learn":[0.4872459436],"iteration":433,"passed_time":4.282261016,"remaining_time":5.58469985},
{"learn":[0.4870619691],"iteration":434,"passed_time":4.286757406,"remaining_time":5.567857321},
{"learn":[0.4866875292],"iteration":435,"passed_time":4.292870521,"remaining_time":5.553162784},
{"learn":[0.4861905214],"iteration":436,"passed_time":4.298051748,"remaining_time":5.537306943},
{"learn":[0.4857227515],"iteration":437,"passed_time":4.307824852,"remaining_time":5.527391705},
{"learn":[0.4854597688],"iteration":438,"passed_time":4.317138647,"remaining_time":5.516890162},
{"learn":[0.4852094524],"iteration":439,"passed_time":4.325290293,"remaining_time":5.504914918},
{"learn":[0.4847207335],"iteration":440,"passed_time":4.330912683,"remaining_time":5.489750997},
{"learn":[0.4844461315],"iteration":441,"passed_time":4.340441171,"remaining_time":5.479561478},
{"learn":[0.4839879884],"iteration":442,"passed_time":4.348548094,"remaining_time":5.467587558},
{"learn":[0.4832353154],"iteration":443,"passed_time":4.356114136,"remaining_time":5.454953737},
{"learn":[0.4829523576],"iteration":444,"passed_time":4.360876925,"remaining_time":5.438846502},
{"learn":[0.4823283154],"iteration":445,"passed_time":4.365999277,"remaining_time":5.42323677},
{"learn":[0.4816335595],"iteration":446,"passed_time":4.374812642,"remaining_time":5.412240248},
{"learn":[0.4812124494],"iteration":447,"passed_time":4.38003044,"remaining_time":5.396823221},
{"learn":[0.4810991907],"iteration":448,"passed_time":4.388137186,"remaining_time":5.384996859},
{"learn":[0.4804633158],"iteration":449,"passed_time":4.392792849,"remaining_time":5.368969037},
{"learn":[0.4799070028],"iteration":450,"passed_time":4.398534551,"remaining_time":5.354313677},
{"learn":[0.4796927086],"iteration":451,"passed_time":4.405424391,"remaining_time":5.341089748},
{"learn":[0.4788161892],"iteration":452,"passed_time":4.412294017,"remaining_time":5.327869376},
{"learn":[0.4779663943],"iteration":453,"passed_time":4.422671604,"remaining_time":5.318895806},
{"learn":[0.4770219413],"iteration":454,"passed_time":4.428881321,"remaining_time":5.30492378},
{"learn":[0.4763140129],"iteration":455,"passed_time":4.440364667,"remaining_time":5.297277147},
{"learn":[0.4754978667],"iteration":456,"passed_time":4.451658293,"remaining_time":5.2893883},
{"learn":[0.4748498588],"iteration":457,"passed_time":4.457893974,"remaining_time":5.275498983},
{"learn":[0.4745278115],"iteration":458,"passed_time":4.4637099,"remaining_time":5.26114827},
{"learn":[0.4741336706],"iteration":459,"passed_time":4.469879003,"remaining_time":5.247249264},
{"learn":[0.4738164191],"iteration":460,"passed_time":4.476778378,"remaining_time":5.234237627},
{"learn":[0.4735141164],"iteration":461,"passed_time":4.487124253,"remaining_time":5.225265905},
{"learn":[0.4733014714],"iteration":462,"passed_time":4.496694477,"remaining_time":5.215388626},
{"learn":[0.4728640136],"iteration":463,"passed_time":4.505923478,"remaining_time":5.2051185},
{"learn":[0.4724348097],"iteration":464,"passed_time":4.514403724,"remaining_time":5.193991381},
{"learn":[0.4718685335],"iteration":465,"passed_time":4.518916555,"remaining_time":5.178329272},
{"learn":[0.4712723813],"iteration":466,"passed_time":4.524036131,"remaining_time":5.163407405},
{"learn":[0.4706777952],"iteration":467,"passed_time":4.529719879,"remaining_time":5.149168751},
{"learn":[0.4702949982],"iteration":468,"passed_time":4.535752137,"remaining_time":5.135361162},
{"learn":[0.4696952697],"iteration":469,"passed_time":4.540565529,"remaining_time":5.120212192},
{"learn":[0.4687294448],"iteration":470,"passed_time":4.550366106,"remaining_time":5.110708429},
{"learn":[0.4684317564],"iteration":471,"passed_time":4.556163694,"remaining_time":5.096725488},
{"learn":[0.4677212731],"iteration":472,"passed_time":4.564000677,"remaining_time":5.08504938},
{"learn":[0.4675602706],"iteration":473,"passed_time":4.570128317,"remaining_time":5.071492605},
{"learn":[0.4670755431],"iteration":474,"passed_time":4.576086488,"remaining_time":5.057779802},
{"learn":[0.4668903929],"iteration":475,"passed_time":4.582418692,"remaining_time":5.044511333},
{"learn":[0.4666359314],"iteration":476,"passed_time":4.588589867,"remaining_time":5.031095389},
{"learn":[0.4665319693],"iteration":477,"passed_time":4.596171532,"remaining_time":5.019250084},
{"learn":[0.4659729558],"iteration":478,"passed_time":4.602085599,"remaining_time":5.005608762},
{"learn":[0.4655986684],"iteration":479,"passed_time":4.610098451,"remaining_time":4.994273322},
{"learn":[0.4648201073],"iteration":480,"passed_time":4.618300487,"remaining_time":4.983155827},
{"learn":[0.4647204672],"iteration":481,"passed_time":4.626588511,"remaining_time":4.972142839},
{"learn":[0.4638947986],"iteration":482,"passed_time":4.631784609,"remaining_time":4.957831558},
{"learn":[0.4633902393],"iteration":483,"passed_time":4.641046844,"remaining_time":4.947892916},
{"learn":[0.4630100759],"iteration":484,"passed_time":4.64792999,"remaining_time":4.935430815},
{"learn":[0.4624109504],"iteration":485,"passed_time":4.654260045,"remaining_time":4.922406715},
{"learn":[0.4620287181],"iteration":486,"passed_time":4.662319708,"remaining_time":4.911232053},
{"learn":[0.461305759],"iteration":487,"passed_time":4.668317207,"remaining_time":4.897906577},
{"learn":[0.4611069894],"iteration":488,"passed_time":4.674304372,"remaining_time":4.884600274},
{"learn":[0.4607318258],"iteration":489,"passed_time":4.679156633,"remaining_time":4.870142618},
{"learn":[0.4603209543],"iteration":490,"passed_time":4.684594974,"remaining_time":4.856331653},
{"learn":[0.4599440208],"iteration":491,"passed_time":4.691155696,"remaining_time":4.843713604},
{"learn":[0.4597992486],"iteration":492,"passed_time":4.697962648,"remaining_time":4.831373352},
{"learn":[0.4594705041],"iteration":493,"passed_time":4.708130853,"remaining_time":4.822498405},
{"learn":[0.4591122938],"iteration":494,"passed_time":4.714973519,"remaining_time":4.810225509},
{"learn":[0.4586977313],"iteration":495,"passed_time":4.731748007,"remaining_time":4.808066524},
{"learn":[0.4583929663],"iteration":496,"passed_time":4.741343165,"remaining_time":4.79858272},
{"learn":[0.4581715535],"iteration":497,"passed_time":4.748381045,"remaining_time":4.786520651},
{"learn":[0.4577020001],"iteration":498,"passed_time":4.76040279,"remaining_time":4.779482561},
{"learn":[0.4571990858],"iteration":499,"passed_time":4.776507159,"remaining_time":4.776507159},
{"learn":[0.4570337155],"iteration":500,"passed_time":4.79196736,"remaining_time":4.77283775},
{"learn":[0.4563630052],"iteration":501,"passed_time":4.826279074,"remaining_time":4.787822667},
{"learn":[0.4563447625],"iteration":502,"passed_time":4.83996874,"remaining_time":4.782235515},
{"learn":[0.4561104758],"iteration":503,"passed_time":4.855319264,"remaining_time":4.778250704},
{"learn":[0.4557367704],"iteration":504,"passed_time":4.861598778,"remaining_time":4.765329495},
{"learn":[0.455020073],"iteration":505,"passed_time":4.873646329,"remaining_time":4.758065784},
{"learn":[0.4549022555],"iteration":506,"passed_time":4.878192509,"remaining_time":4.743488968},
{"learn":[0.4544975807],"iteration":507,"passed_time":4.892091455,"remaining_time":4.738009835},
{"learn":[0.454229961],"iteration":508,"passed_time":4.939579948,"remaining_time":4.764899321},
{"learn":[0.4537002121],"iteration":509,"passed_time":4.955663131,"remaining_time":4.7613234},
{"learn":[0.4532055832],"iteration":510,"passed_time":4.965167549,"remaining_time":4.751402997},
{"learn":[0.4528769975],"iteration":511,"passed_time":4.97198898,"remaining_time":4.738926997},
{"learn":[0.4520501943],"iteration":512,"passed_time":4.985442355,"remaining_time":4.732768863},
{"learn":[0.4517039173],"iteration":513,"passed_time":4.997536721,"remaining_time":4.725297367},
{"learn":[0.4509116045],"iteration":514,"passed_time":5.006448352,"remaining_time":4.714810584},
{"learn":[0.4500069394],"iteration":515,"passed_time":5.018432527,"remaining_time":4.707211906},
{"learn":[0.4497347648],"iteration":516,"passed_time":5.029601091,"remaining_time":4.698834288},
{"learn":[0.449442938],"iteration":517,"passed_time":5.038662473,"remaining_time":4.688485158},
{"learn":[0.4492518282],"iteration":518,"passed_time":5.050003776,"remaining_time":4.680253982},
{"learn":[0.448723576],"iteration":519,"passed_time":5.067581423,"remaining_time":4.677767467},
{"learn":[0.4485792164],"iteration":520,"passed_time":5.078071219,"remaining_time":4.668706553},
{"learn":[0.4481299073],"iteration":521,"passed_time":5.086427367,"remaining_time":4.657686363},
{"learn":[0.4477111941],"iteration":522,"passed_time":5.096184565,"remaining_time":4.647954183},
{"learn":[0.4476432542],"iteration":523,"passed_time":5.100548039,"remaining_time":4.633322264},
{"learn":[0.447058925],"iteration":524,"passed_time":5.104542484,"remaining_time":4.61839558},
{"learn":[0.4464812051],"iteration":525,"passed_time":5.111746878,"remaining_time":4.60640308},
{"learn":[0.446279968],"iteration":526,"passed_time":5.117506154,"remaining_time":4.59313171},
{"learn":[0.4454177836],"iteration":527,"passed_time":5.126898408,"remaining_time":4.583136456},
{"learn":[0.4453226004],"iteration":528,"passed_time":5.143540296,"remaining_time":4.57959826},
{"learn":[0.4450873623],"iteration":529,"passed_time":5.158362487,"remaining_time":4.574396922},
{"learn":[0.444898451],"iteration":530,"passed_time":5.165044942,"remaining_time":4.561970014},
{"learn":[0.4447007331],"iteration":531,"passed_time":5.177638043,"remaining_time":4.554764293},
{"learn":[0.4444917856],"iteration":532,"passed_time":5.191313863,"remaining_time":4.548487005},
{"learn":[0.4440290639],"iteration":533,"passed_time":5.198195672,"remaining_time":4.536253152},
{"learn":[0.4431426339],"iteration":534,"passed_time":5.207743004,"remaining_time":4.526356069},
{"learn":[0.4428500682],"iteration":535,"passed_time":5.212143709,"remaining_time":4.512005002},
{"learn":[0.4427460497],"iteration":536,"passed_time":5.221960599,"remaining_time":4.502360815},
{"learn":[0.4421469804],"iteration":537,"passed_time":5.229786757,"remaining_time":4.491006472},
{"learn":[0.4417924065],"iteration":538,"passed_time":5.239747158,"remaining_time":4.481490612},
{"learn":[0.4416598429],"iteration":539,"passed_time":5.245538956,"remaining_time":4.468422073},
{"learn":[0.4414940239],"iteration":540,"passed_time":5.255014847,"remaining_time":4.458506127},
{"learn":[0.4408590097],"iteration":541,"passed_time":5.260626751,"remaining_time":4.445326664},
{"learn":[0.4404631403],"iteration":542,"passed_time":5.268843491,"remaining_time":4.434367358},
{"learn":[0.4400245464],"iteration":543,"passed_time":5.274465005,"remaining_time":4.421242725},
{"learn":[0.4396197062],"iteration":544,"passed_time":5.278774041,"remaining_time":4.407049887},
{"learn":[0.4395035813],"iteration":545,"passed_time":5.285874722,"remaining_time":4.395214512},
{"learn":[0.4392513203],"iteration":546,"passed_time":5.297053889,"remaining_time":4.386774062},
{"learn":[0.4385913742],"iteration":547,"passed_time":5.306223499,"remaining_time":4.376666097},
{"learn":[0.4384362757],"iteration":548,"passed_time":5.318667857,"remaining_time":4.369251737},
{"learn":[0.4381831372],"iteration":549,"passed_time":5.323775596,"remaining_time":4.355816397},
{"learn":[0.4377276666],"iteration":550,"passed_time":5.329459559,"remaining_time":4.342880839},
{"learn":[0.437353298],"iteration":551,"passed_time":5.33547375,"remaining_time":4.330239565},
{"learn":[0.4370193711],"iteration":552,"passed_time":5.341757134,"remaining_time":4.317839853},
{"learn":[0.4365150781],"iteration":553,"passed_time":5.349272516,"remaining_time":4.306454047},
{"learn":[0.4363867978],"iteration":554,"passed_time":5.354577774,"remaining_time":4.293310107},
{"learn":[0.4360302179],"iteration":555,"passed_time":5.364946429,"remaining_time":4.284237796},
{"learn":[0.435823254],"iteration":556,"passed_time":5.370722283,"remaining_time":4.271508028},
{"learn":[0.4351226586],"iteration":557,"passed_time":5.381360716,"remaining_time":4.262654904},
{"learn":[0.4350004889],"iteration":558,"passed_time":5.388757641,"remaining_time":4.251238139},
{"learn":[0.4348583359],"iteration":559,"passed_time":5.395670494,"remaining_time":4.239455388},
{"learn":[0.4344053904],"iteration":560,"passed_time":5.401514692,"remaining_time":4.226853743},
{"learn":[0.4343123819],"iteration":561,"passed_time":5.421649075,"remaining_time":4.225413336},
{"learn":[0.4340207333],"iteration":562,"passed_time":5.441175593,"remaining_time":4.223434697},
{"learn":[0.4332964792],"iteration":563,"passed_time":5.45876032,"remaining_time":4.219892729},
{"learn":[0.4329436973],"iteration":564,"passed_time":5.486813076,"remaining_time":4.22436051},
{"learn":[0.4326279532],"iteration":565,"passed_time":5.521293676,"remaining_time":4.233642147},
{"learn":[0.4323461217],"iteration":566,"passed_time":5.528796794,"remaining_time":4.222167569},
{"learn":[0.4313185388],"iteration":567,"passed_time":5.549270134,"remaining_time":4.220571651},
{"learn":[0.4308252689],"iteration":568,"passed_time":5.560053373,"remaining_time":4.211569427},
{"learn":[0.4304143548],"iteration":569,"passed_time":5.564924736,"remaining_time":4.198101116},
{"learn":[0.4298108506],"iteration":570,"passed_time":5.573193787,"remaining_time":4.187215647},
{"learn":[0.4296650619],"iteration":571,"passed_time":5.579977297,"remaining_time":4.175227768},
{"learn":[0.4292602951],"iteration":572,"passed_time":5.589200483,"remaining_time":4.165076102},
{"learn":[0.4287550945],"iteration":573,"passed_time":5.59549493,"remaining_time":4.152754077},
{"learn":[0.428011919],"iteration":574,"passed_time":5.610171415,"remaining_time":4.146648438},
{"learn":[0.4275787141],"iteration":575,"passed_time":5.62323246,"remaining_time":4.139323894},
{"learn":[0.4274635371],"iteration":576,"passed_time":5.637215037,"remaining_time":4.132655045},
{"learn":[0.4271786841],"iteration":577,"passed_time":5.649469544,"remaining_time":4.124699217},
{"learn":[0.4270705634],"iteration":578,"passed_time":5.655440106,"remaining_time":4.112159387},
{"learn":[0.4268268214],"iteration":579,"passed_time":5.663083625,"remaining_time":4.100853659},
{"learn":[0.4266287804],"iteration":580,"passed_time":5.669797734,"remaining_time":4.088890276},
{"learn":[0.4265138955],"iteration":581,"passed_time":5.678907698,"remaining_time":4.078665666},
{"learn":[0.4259906482],"iteration":582,"passed_time":5.68731007,"remaining_time":4.067938764},
{"learn":[0.4252489513],"iteration":583,"passed_time":5.696257511,"remaining_time":4.05760809},
{"learn":[0.4247576039],"iteration":584,"passed_time":5.703503801,"remaining_time":4.046075346},
{"learn":[0.4240164284],"iteration":585,"passed_time":5.709732709,"remaining_time":4.033838467},
{"learn":[0.4231748281],"iteration":586,"passed_time":5.715568573,"remaining_time":4.021345521},
{"learn":[0.4227307239],"iteration":587,"passed_time":5.720994123,"remaining_time":4.008587719},
{"learn":[0.4218970856],"iteration":588,"passed_time":5.728206515,"remaining_time":3.99710166},
{"learn":[0.421702786],"iteration":589,"passed_time":5.737949282,"remaining_time":3.987388484},
{"learn":[0.4214494042],"iteration":590,"passed_time":5.747498964,"remaining_time":3.977541584},
{"learn":[0.4206170372],"iteration":591,"passed_time":5.752056374,"remaining_time":3.964255068},
{"learn":[0.4204358436],"iteration":592,"passed_time":5.758794452,"remaining_time":3.952494674},
{"learn":[0.4200329298],"iteration":593,"passed_time":5.764780391,"remaining_time":3.940237103},
{"learn":[0.4194163591],"iteration":594,"passed_time":5.774200291,"remaining_time":3.930338013},
{"learn":[0.418744878],"iteration":595,"passed_time":5.780462941,"remaining_time":3.918300383},
{"learn":[0.4185029052],"iteration":596,"passed_time":5.792359258,"remaining_time":3.910085061},
{"learn":[0.4184523019],"iteration":597,"passed_time":5.798359534,"remaining_time":3.897893868},
{"learn":[0.418017817],"iteration":598,"passed_time":5.807038987,"remaining_time":3.887516918},
{"learn":[0.4175757401],"iteration":599,"passed_time":5.813898055,"remaining_time":3.875932037},
{"learn":[0.4173595396],"iteration":600,"passed_time":5.828802796,"remaining_time":3.869704352},
{"learn":[0.417005195],"iteration":601,"passed_time":5.835762346,"remaining_time":3.85819504},
{"learn":[0.4166603494],"iteration":602,"passed_time":5.843853112,"remaining_time":3.847445581},
{"learn":[0.4164392741],"iteration":603,"passed_time":5.848686293,"remaining_time":3.834569159},
{"learn":[0.4159155199],"iteration":604,"passed_time":5.857093421,"remaining_time":3.82405273},
{"learn":[0.415744957],"iteration":605,"passed_time":5.863223516,"remaining_time":3.812062814},
{"learn":[0.4151406397],"iteration":606,"passed_time":5.870308983,"remaining_time":3.800710758},
{"learn":[0.4147115867],"iteration":607,"passed_time":5.876916831,"remaining_time":3.789064799},
{"learn":[0.414131793],"iteration":608,"passed_time":5.881252492,"remaining_time":3.775976559},
{"learn":[0.413677241],"iteration":609,"passed_time":5.886995839,"remaining_time":3.763817012},
{"learn":[0.4136081995],"iteration":610,"passed_time":5.892207529,"remaining_time":3.751339982},
{"learn":[0.413492679],"iteration":611,"passed_time":5.898035607,"remaining_time":3.739277477},
{"learn":[0.4130957701],"iteration":612,"passed_time":5.904675179,"remaining_time":3.727747625},
{"learn":[0.4127405966],"iteration":613,"passed_time":5.908889656,"remaining_time":3.714709132},
{"learn":[0.4125364465],"iteration":614,"passed_time":5.92340204,"remaining_time":3.708145992},
{"learn":[0.4123166203],"iteration":615,"passed_time":5.938023376,"remaining_time":3.701624962},
{"learn":[0.4120839734],"iteration":616,"passed_time":5.955655254,"remaining_time":3.696946454},
{"learn":[0.4114205836],"iteration":617,"passed_time":5.969282577,"remaining_time":3.689750719},
{"learn":[0.4108174411],"iteration":618,"passed_time":5.973762788,"remaining_time":3.676904075},
{"learn":[0.4106837552],"iteration":619,"passed_time":5.983365173,"remaining_time":3.667223816},
{"learn":[0.4101291453],"iteration":620,"passed_time":5.98934653,"remaining_time":3.655333873},
{"learn":[0.4096106905],"iteration":621,"passed_time":5.996432654,"remaining_time":3.644134314},
{"learn":[0.4092773207],"iteration":622,"passed_time":6.003928181,"remaining_time":3.633195705},
{"learn":[0.4089090256],"iteration":623,"passed_time":6.008856898,"remaining_time":3.620721464},
{"learn":[0.4085213486],"iteration":624,"passed_time":6.015903291,"remaining_time":3.609541975},
{"learn":[0.4083584239],"iteration":625,"passed_time":6.020392215,"remaining_time":3.596847745},
{"learn":[0.4081619301],"iteration":626,"passed_time":6.02588696,"remaining_time":3.584778048},
{"learn":[0.4081002468],"iteration":627,"passed_time":6.032633934,"remaining_time":3.573471056},
{"learn":[0.4077848394],"iteration":628,"passed_time":6.037379977,"remaining_time":3.560998365},
{"learn":[0.4072407901],"iteration":629,"passed_time":6.046748048,"remaining_time":3.551264727},
{"learn":[0.4069993888],"iteration":630,"passed_time":6.052163793,"remaining_time":3.539220982},
{"learn":[0.4068420084],"iteration":631,"passed_time":6.06028111,"remaining_time":3.528771279},
{"learn":[0.4065801732],"iteration":632,"passed_time":6.066787414,"remaining_time":3.517394915},
{"learn":[0.4062626067],"iteration":633,"passed_time":6.071367492,"remaining_time":3.504921928},
{"learn":[0.4061766991],"iteration":634,"passed_time":6.077840198,"remaining_time":3.493561689},
{"learn":[0.4059482728],"iteration":635,"passed_time":6.083589352,"remaining_time":3.481802711},
{"learn":[0.4056052404],"iteration":636,"passed_time":6.090253552,"remaining_time":3.470584049},
{"learn":[0.4053119264],"iteration":637,"passed_time":6.096972151,"remaining_time":3.459410531},
{"learn":[0.4050137935],"iteration":638,"passed_time":6.101610263,"remaining_time":3.447075594},
{"learn":[0.4043924913],"iteration":639,"passed_time":6.110091582,"remaining_time":3.436926515},
{"learn":[0.4041697716],"iteration":640,"passed_time":6.116571898,"remaining_time":3.425661952},
{"learn":[0.403963565],"iteration":641,"passed_time":6.124580745,"remaining_time":3.415264652},
{"learn":[0.403608411],"iteration":642,"passed_time":6.130841538,"remaining_time":3.403904244},
{"learn":[0.4031711288],"iteration":643,"passed_time":6.139518952,"remaining_time":3.39389557},
{"learn":[0.4030568772],"iteration":644,"passed_time":6.145258478,"remaining_time":3.382274046},
{"learn":[0.4028312332],"iteration":645,"passed_time":6.153906231,"remaining_time":3.372264405},
{"learn":[0.4025895706],"iteration":646,"passed_time":6.161419731,"remaining_time":3.361640132},
{"learn":[0.4023718127],"iteration":647,"passed_time":6.168969642,"remaining_time":3.351045238},
{"learn":[0.4022457924],"iteration":648,"passed_time":6.176633936,"remaining_time":3.34052159},
{"learn":[0.402045402],"iteration":649,"passed_time":6.181436516,"remaining_time":3.328465817},
{"learn":[0.4017711179],"iteration":650,"passed_time":6.187931062,"remaining_time":3.317339387},
{"learn":[0.4009301045],"iteration":651,"passed_time":6.193880203,"remaining_time":3.305936059},
{"learn":[0.4005577912],"iteration":652,"passed_time":6.203350022,"remaining_time":3.296420303},
{"learn":[0.4003123096],"iteration":653,"passed_time":6.208927727,"remaining_time":3.284845556},
{"learn":[0.3999567031],"iteration":654,"passed_time":6.216516106,"remaining_time":3.274348178},
{"learn":[0.399463129],"iteration":655,"passed_time":6.223366325,"remaining_time":3.263472585},
{"learn":[0.3989495846],"iteration":656,"passed_time":6.22889298,"remaining_time":3.251918253},
{"learn":[0.3985833149],"iteration":657,"passed_time":6.236823308,"remaining_time":3.241631567},
{"learn":[0.3984411272],"iteration":658,"passed_time":6.241880413,"remaining_time":3.229865282},
{"learn":[0.3981827667],"iteration":659,"passed_time":6.24960104,"remaining_time":3.219491445},
{"learn":[0.3980982002],"iteration":660,"passed_time":6.256846593,"remaining_time":3.208881989},
{"learn":[0.3979951358],"iteration":661,"passed_time":6.270513637,"remaining_time":3.201561343},
{"learn":[0.3977804265],"iteration":662,"passed_time":6.279922899,"remaining_time":3.192057341},
{"learn":[0.3972773005],"iteration":663,"passed_time":6.286773192,"remaining_time":3.181258724},
{"learn":[0.3965070885],"iteration":664,"passed_time":6.297189241,"remaining_time":3.172268264},
{"learn":[0.3964533752],"iteration":665,"passed_time":6.30903875,"remaining_time":3.163992406},
{"learn":[0.3961799968],"iteration":666,"passed_time":6.31753483,"remaining_time":3.154031632},
{"learn":[0.3955566488],"iteration":667,"passed_time":6.326505446,"remaining_time":3.14431109},
{"learn":[0.3954477767],"iteration":668,"passed_time":6.33467908,"remaining_time":3.134198469},
{"learn":[0.3952861609],"iteration":669,"passed_time":6.343549421,"remaining_time":3.12443479},
{"learn":[0.3946567191],"iteration":670,"passed_time":6.349973095,"remaining_time":3.113474141},
{"learn":[0.3944581513],"iteration":671,"passed_time":6.354899764,"remaining_time":3.101796314},
{"learn":[0.3943794637],"iteration":672,"passed_time":6.364384963,"remaining_time":3.092353466},
{"learn":[0.3941221688],"iteration":673,"passed_time":6.371520515,"remaining_time":3.081774018},
{"learn":[0.3935655138],"iteration":674,"passed_time":6.380475387,"remaining_time":3.072080742},
{"learn":[0.3933727592],"iteration":675,"passed_time":6.39667593,"remaining_time":3.065862428},
{"learn":[0.3932531761],"iteration":676,"passed_time":6.412833518,"remaining_time":3.059594131},
{"learn":[0.3927284017],"iteration":677,"passed_time":6.418896493,"remaining_time":3.048502464},
{"learn":[0.3923191673],"iteration":678,"passed_time":6.427867668,"remaining_time":3.038800473},
{"learn":[0.3920086425],"iteration":679,"passed_time":6.440865135,"remaining_time":3.030995358},
{"learn":[0.3914723052],"iteration":680,"passed_time":6.4478429,"remaining_time":3.020355191},
{"learn":[0.3913408436],"iteration":681,"passed_time":6.456286705,"remaining_time":3.010409343},
{"learn":[0.3913019153],"iteration":682,"passed_time":6.462765698,"remaining_time":2.999555968},
{"learn":[0.3910658792],"iteration":683,"passed_time":6.470429298,"remaining_time":2.989262658},
{"learn":[0.3907483767],"iteration":684,"passed_time":6.476576531,"remaining_time":2.978279719},
{"learn":[0.3901971991],"iteration":685,"passed_time":6.481375424,"remaining_time":2.966693707},
{"learn":[0.3896809053],"iteration":686,"passed_time":6.488155764,"remaining_time":2.95603021},
{"learn":[0.3890751948],"iteration":687,"passed_time":6.49310285,"remaining_time":2.944546641},
{"learn":[0.388732292],"iteration":688,"passed_time":6.498991096,"remaining_time":2.933506866},
{"learn":[0.3882387706],"iteration":689,"passed_time":6.506267742,"remaining_time":2.923105797},
{"learn":[0.3881434317],"iteration":690,"passed_time":6.515218302,"remaining_time":2.913462309},
{"learn":[0.3879214008],"iteration":691,"passed_time":6.52632688,"remaining_time":2.904781328},
{"learn":[0.387631612],"iteration":692,"passed_time":6.535664198,"remaining_time":2.895308671},
{"learn":[0.3870502689],"iteration":693,"passed_time":6.541562373,"remaining_time":2.884320009},
{"learn":[0.386614357],"iteration":694,"passed_time":6.555817316,"remaining_time":2.877013354},
{"learn":[0.386461612],"iteration":695,"passed_time":6.563965823,"remaining_time":2.867019555},
{"learn":[0.3863681206],"iteration":696,"passed_time":6.571079965,"remaining_time":2.856581391},
{"learn":[0.3861005643],"iteration":697,"passed_time":6.579657489,"remaining_time":2.846785905},
{"learn":[0.3857824135],"iteration":698,"passed_time":6.586834812,"remaining_time":2.836390956},
{"learn":[0.3851681022],"iteration":699,"passed_time":6.595050865,"remaining_time":2.826450371},
{"learn":[0.3848628551],"iteration":700,"passed_time":6.603316185,"remaining_time":2.816535719},
{"learn":[0.3843019091],"iteration":701,"passed_time":6.612025944,"remaining_time":2.806814432},
{"learn":[0.3842382103],"iteration":702,"passed_time":6.621587992,"remaining_time":2.797456093},
{"learn":[0.3837160034],"iteration":703,"passed_time":6.628858319,"remaining_time":2.787133612},
{"learn":[0.3832854173],"iteration":704,"passed_time":6.635441276,"remaining_time":2.776532165},
{"learn":[0.3831179155],"iteration":705,"passed_time":6.643212474,"remaining_time":2.766436922},
{"learn":[0.3825935539],"iteration":706,"passed_time":6.649453388,"remaining_time":2.755714063},
{"learn":[0.3824870068],"iteration":707,"passed_time":6.658075442,"remaining_time":2.745985917},
{"learn":[0.3822123695],"iteration":708,"passed_time":6.665110826,"remaining_time":2.735609662},
{"learn":[0.3817962556],"iteration":709,"passed_time":6.709716816,"remaining_time":2.740588559},
{"learn":[0.3812753722],"iteration":710,"passed_time":6.716780264,"remaining_time":2.730168068},
{"learn":[0.3808938274],"iteration":711,"passed_time":6.72512641,"remaining_time":2.720275851},
{"learn":[0.3808287506],"iteration":712,"passed_time":6.731247425,"remaining_time":2.709492302},
{"learn":[0.3804245574],"iteration":713,"passed_time":6.766312952,"remaining_time":2.710315832},
{"learn":[0.3800540376],"iteration":714,"passed_time":6.77460803,"remaining_time":2.700368236},
{"learn":[0.3794784916],"iteration":715,"passed_time":6.782945223,"remaining_time":2.69044196},
{"learn":[0.3793037923],"iteration":716,"passed_time":6.792117343,"remaining_time":2.680849662},
{"learn":[0.3788082411],"iteration":717,"passed_time":6.825754887,"remaining_time":2.680867518},
{"learn":[0.3785292597],"iteration":718,"passed_time":6.836628405,"remaining_time":2.671895107},
{"learn":[0.3782637119],"iteration":719,"passed_time":6.866949715,"remaining_time":2.670480445},
{"learn":[0.377767411],"iteration":720,"passed_time":6.877152198,"remaining_time":2.661200365},
{"learn":[0.3773496911],"iteration":721,"passed_time":6.886986903,"remaining_time":2.651776121},
{"learn":[0.3767161286],"iteration":722,"passed_time":6.911150858,"remaining_time":2.647840647},
{"learn":[0.376486281],"iteration":723,"passed_time":6.918328441,"remaining_time":2.637373826},
{"learn":[0.3760280856],"iteration":724,"passed_time":6.927247832,"remaining_time":2.627576764},
{"learn":[0.3759748659],"iteration":725,"passed_time":6.937723849,"remaining_time":2.618369607},
{"learn":[0.3757241574],"iteration":726,"passed_time":6.945658036,"remaining_time":2.608204462},
{"learn":[0.375514598],"iteration":727,"passed_time":6.954637379,"remaining_time":2.598435944},
{"learn":[0.3752107459],"iteration":728,"passed_time":6.961270056,"remaining_time":2.587797236},
{"learn":[0.374791109],"iteration":729,"passed_time":6.972365628,
{"learn":[0.3737500348],"ite,
{"learn":[0.3745762778],"iteration":730,"passed_time":6.98382827,,
{"learn":[0.3736627034],"it,
{"learn":[0.3743232232],"iteration":731,"passed_time":6.99010173,",
{"learn":[0.3731970774],"iteration":732,"passed_time":6.845042642,"remaining_time":2.49335114},
{"learn":[0.3730221259],"iteration":733,"passed_time":6.857201693,"remaining_time":2.485034946},
{"learn":[0.3729678196],"iteration":734,"passed_time":6.874256197,"remaining_time":2.478473323},
{"learn":[0.3729006165],"iteration":735,"passed_time":6.880806757,"remaining_time":2.468115467},
{"learn":[0.372646843],"iteration":736,"passed_time":6.890001808,"remaining_time":2.458711636},
{"learn":[0.3719852369],"iteration":737,"passed_time":6.904776464,"remaining_time":2.451289205},
{"learn":[0.3717427419],"iteration":738,"passed_time":6.913656617,"remaining_time":2.441765057},
{"learn":[0.3712624884],"iteration":739,"passed_time":6.923641748,"remaining_time":2.432630884},
{"learn":[0.371044062],"iteration":740,"passed_time":6.934296982,"remaining_time":2.423728635},
{"learn":[0.3708947842],"iteration":741,"passed_time":6.942016397,"remaining_time":2.413800849},
{"learn":[0.3708527407],"iteration":742,"passed_time":6.952088771,"remaining_time":2.404692886},
{"learn":[0.3707489443],"iteration":743,"passed_time":6.959771892,"remaining_time":2.394760221},
{"learn":[0.3703327014],"iteration":744,"passed_time":6.967171216,"remaining_time":2.384736457},
{"learn":[0.3702898132],"iteration":745,"passed_time":6.971168774,"remaining_time":2.373561486},
{"learn":[0.3697967556],"iteration":746,"passed_time":7.009516763,"remaining_time":2.374039814},
{"learn":[0.3695577938],"iteration":747,"passed_time":7.018605863,"remaining_time":2.364557056},
{"learn":[0.3694538415],"iteration":748,"passed_time":7.0257754,"remaining_time":2.354432076},
{"learn":[0.3690480646],"iteration":749,"passed_time":7.036411293,"remaining_time":2.345470431},
{"learn":[0.3689687091],"iteration":750,"passed_time":7.040570956,"remaining_time":2.334357081},
{"learn":[0.3686344894],"iteration":751,"passed_time":7.047956819,"remaining_time":2.324326185},
{"learn":[0.3682457135],"iteration":752,"passed_time":7.057483828,"remaining_time":2.315004655},
{"learn":[0.3681068261],"iteration":753,"passed_time":7.064208766,"remaining_time":2.304768377},
{"learn":[0.3679586284],"iteration":754,"passed_time":7.082841254,"remaining_time":2.29840544},
{"learn":[0.3676451655],"iteration":755,"passed_time":7.09030452,"remaining_time":2.288405163},
{"learn":[0.3674860653],"iteration":756,"passed_time":7.096765152,"remaining_time":2.278089738},
{"learn":[0.3669578843],"iteration":757,"passed_time":7.105946474,"remaining_time":2.268653096},
{"learn":[0.3668082736],"iteration":758,"passed_time":7.116293422,"remaining_time":2.259587239},
{"learn":[0.3667369458],"iteration":759,"passed_time":7.121405671,"remaining_time":2.248864949},
{"learn":[0.366532218],"iteration":760,"passed_time":7.13044956,"remaining_time":2.239392175},
{"learn":[0.3661246345],"iteration":761,"passed_time":7.137579711,"remaining_time":2.229322797},
{"learn":[0.3657325797],"iteration":762,"passed_time":7.144517578,"remaining_time":2.219201397},
{"learn":[0.3655064095],"iteration":763,"passed_time":7.149916619,"remaining_time":2.208612987},
{"learn":[0.3650071698],"iteration":764,"passed_time":7.154834284,"remaining_time":2.19789027},
{"learn":[0.3649281616],"iteration":765,"passed_time":7.161907782,"remaining_time":2.187841281},
{"learn":[0.3648808006],"iteration":766,"passed_time":7.1672344,"remaining_time":2.177269381},
{"learn":[0.3647613753],"iteration":767,"passed_time":7.176363388,"remaining_time":2.167859774},
{"learn":[0.3645101055],"iteration":768,"passed_time":7.183049118,"remaining_time":2.157716965},
{"learn":[0.3642491297],"iteration":769,"passed_time":7.188547534,"remaining_time":2.147228484},
{"learn":[0.3640510177],"iteration":770,"passed_time":7.19596157,"remaining_time":2.137321919},
{"learn":[0.3640120639],"iteration":771,"passed_time":7.198555221,"remaining_time":2.125998174},
{"learn":[0.3637147814],"iteration":772,"passed_time":7.209000336,"remaining_time":2.117002686},
{"learn":[0.363287429],"iteration":773,"passed_time":7.215793707,"remaining_time":2.106937181},
{"learn":[0.3630160823],"iteration":774,"passed_time":7.223115288,"remaining_time":2.097033471},
{"learn":[0.3629367738],"iteration":775,"passed_time":7.230431963,"remaining_time":2.087135},
{"learn":[0.3626141156],"iteration":776,"passed_time":7.234634196,"remaining_time":2.076349325},
{"learn":[0.3623064341],"iteration":777,"passed_time":7.243608425,"remaining_time":2.06694225},
{"learn":[0.3619501107],"iteration":778,"passed_time":7.248750165,"remaining_time":2.05644902},
{"learn":[0.3615679811],"iteration":779,"passed_time":7.25817895,"remaining_time":2.047178678},
{"learn":[0.3613877188],"iteration":780,"passed_time":7.26452883,"remaining_time":2.037044576},
{"learn":[0.3612619944],"iteration":781,"passed_time":7.27204168,"remaining_time":2.027244356},
{"learn":[0.361156393],"iteration":782,"passed_time":7.277465769,"remaining_time":2.016871101},
{"learn":[0.3608517247],"iteration":783,"passed_time":7.282937044,"remaining_time":2.006523471},
{"learn":[0.3605775897],"iteration":784,"passed_time":7.289019632,"remaining_time":1.996355695},
{"learn":[0.3602133536],"iteration":785,"passed_time":7.293861626,"remaining_time":1.985860544},
{"learn":[0.359923007],"iteration":786,"passed_time":7.298786871,"remaining_time":1.975402292},
{"learn":[0.3596795163],"iteration":787,"passed_time":7.305598805,"remaining_time":1.965465668},
{"learn":[0.3595206066],"iteration":788,"passed_time":7.309585657,"remaining_time":1.954781462},
{"learn":[0.3593283515],"iteration":789,"passed_time":7.317515795,"remaining_time":1.945162427},
{"learn":[0.3589099196],"iteration":790,"passed_time":7.327184114,"remaining_time":1.936006928},
{"learn":[0.3588423876],"iteration":791,"passed_time":7.334120275,"remaining_time":1.926132598},
{"learn":[0.3586708851],"iteration":792,"passed_time":7.339411858,"remaining_time":1.915836387},
{"learn":[0.3584657506],"iteration":793,"passed_time":7.346390805,"remaining_time":1.905990562},
{"learn":[0.3580234351],"iteration":794,"passed_time":7.354338017,"remaining_time":1.896401627},
{"learn":[0.357797588],"iteration":795,"passed_time":7.363554606,"remaining_time":1.887142135},
{"learn":[0.3576804367],"iteration":796,"passed_time":7.36942268,"remaining_time":1.877029867},
{"learn":[0.3572583298],"iteration":797,"passed_time":7.375446868,"remaining_time":1.866967754},
{"learn":[0.3569873646],"iteration":798,"passed_time":7.384034136,"remaining_time":1.857560527},
{"learn":[0.3566047512],"iteration":799,"passed_time":7.389203074,"remaining_time":1.847300769},
{"learn":[0.3563358369],"iteration":800,"passed_time":7.396275146,"remaining_time":1.837526534},
{"learn":[0.355941998],"iteration":801,"passed_time":7.400956198,"remaining_time":1.827168737},
{"learn":[0.3557982469],"iteration":802,"passed_time":7.405360342,"remaining_time":1.816757145},
{"learn":[0.3554706822],"iteration":803,"passed_time":7.412424698,"remaining_time":1.807009006},
{"learn":[0.3553563797],"iteration":804,"passed_time":7.417414674,"remaining_time":1.796765045},
{"learn":[0.3550281505],"iteration":805,"passed_time":7.422302485,"remaining_time":1.786509531},
{"learn":[0.3548145652],"iteration":806,"passed_time":7.430016298,"remaining_time":1.776943179},
{"learn":[0.3544640297],"iteration":807,"passed_time":7.43483777,"remaining_time":1.766694123},
{"learn":[0.3543926604],"iteration":808,"passed_time":7.439139768,"remaining_time":1.756335842},
{"learn":[0.3541402585],"iteration":809,"passed_time":7.445790179,"remaining_time":1.746543375},
{"learn":[0.3538250401],"iteration":810,"passed_time":7.451789602,"remaining_time":1.736606948},
{"learn":[0.3535788295],"iteration":811,"passed_time":7.458842779,"remaining_time":1.72692419},
{"learn":[0.3534806754],"iteration":812,"passed_time":7.465523556,"remaining_time":1.717162245},
{"learn":[0.3533290956],"iteration":813,"passed_time":7.474140131,"remaining_time":1.707850202},
{"learn":[0.3532649147],"iteration":814,"passed_time":7.479327286,"remaining_time":1.697761409},
{"learn":[0.3530629948],"iteration":815,"passed_time":7.483796611,"remaining_time":1.687522765},
{"learn":[0.3528769481],"iteration":816,"passed_time":7.491940154,"remaining_time":1.678121234},
{"learn":[0.352766611],"iteration":817,"passed_time":7.497202137,"remaining_time":1.668081649},
{"learn":[0.3526562376],"iteration":818,"passed_time":7.501082331,"remaining_time":1.657748354},
{"learn":[0.3523581088],"iteration":819,"passed_time":7.506521134,"remaining_time":1.647772932},
{"learn":[0.3520524923],"iteration":820,"passed_time":7.510461825,"remaining_time":1.637481933},
{"learn":[0.3518304959],"iteration":821,"passed_time":7.515108065,"remaining_time":1.627359167},
{"learn":[0.3516557784],"iteration":822,"passed_time":7.521160087,"remaining_time":1.617552048},
{"learn":[0.3513693363],"iteration":823,"passed_time":7.525916757,"remaining_time":1.607477366},
{"learn":[0.350936454],"iteration":824,"passed_time":7.530274577,"remaining_time":1.597330971},
{"learn":[0.3505766687],"iteration":825,"passed_time":7.53609555,"remaining_time":1.587506811},
{"learn":[0.350176139],"iteration":826,"passed_time":7.540644131,"remaining_time":1.577426161},
{"learn":[0.349878044],"iteration":827,"passed_time":7.545331944,"remaining_time":1.567387795},
{"learn":[0.3495885309],"iteration":828,"passed_time":7.553094723,"remaining_time":1.55799662},
{"learn":[0.3493992802],"it,
{"learn":[0.3487141416],"iteration":829,"passed_time":7.720934518,
{"learn":[0.3491728106],"ite,
{"learn":[0.3486396651],"iteration":830,"passed_time":7.728856499,
{"learn":[0.34911519],"itera,
{"learn":[0.3482803548],"iteration":831,"passed_time":7.7348809,
{"learn":[0.3487582722],"iter,
{"learn":[0.3477125102],"iteration":832,"passed_time":7.74239180,
{"learn":[0.3484693292],"iter,
{"learn":[0.3473169451],"iteration":833,"passed_time":7.74755614,
{"learn":[0.3481643768],"ite,
{"learn":[0.3468611252],"iteration":834,"passed_time":7.752656077,
{"learn":[0.3480905648],"iteration":835,"passed_time":7.599866735,"remaining_time":1.490882948},
{"learn":[0.3478351948],"iteration":836,"passed_time":7.607325432,"remaining_time":1.481474367},
{"learn":[0.3474997577],"iteration":837,"passed_time":7.614462819,"remaining_time":1.472008325},
{"learn":[0.3472465587],"iteration":838,"passed_time":7.620920196,"remaining_time":1.462417344},
{"learn":[0.3470493334],"iteration":839,"passed_time":7.625805688,"remaining_time":1.452534417},
{"learn":[0.3466897138],"it,
{"learn":[0.3459442673],"iteration":840,"passed_time":7.790302251,,
{"learn":[0.3465752224],"iteration":841,"passed_time":7.636947537,"remaining_time":1.433061414},
{"learn":[0.3463650683],",
{"learn":[0.3455291323],"iteration":842,"passed_time":7.80164007,"r,
{"learn":[0.3461747445],",
{"learn":[0.345203739],"iteration":843,"passed_time":7.810198515,"re,
{"learn":[0.3461165332],,
{"learn":[0.344983374],"iteration":844,"passed_time":7.815808422,"rem,
{"learn":[0.34608675,
{"learn":[0.3446938695],"iteration":845,"passed_time":7.82154086,"remaini,
{"learn":[0.3458011255],"iteration":846,"passed_time":7.671220115,"remaining_time":1.385710363},
{"learn":[0.3456353863],"iteration":847,"passed_time":7.679964949,"remaining_time":1.376597491},
{"learn":[0.3453673873],"iteration":848,"passed_time":7.685443022,"remaining_time":1.366904472},
{"learn":[0.3449942,
{"learn":[0.3438117466],"iteration":849,"passed_time":7.85433721,"remaini,
{"learn":[0.3447569,
{"learn":[0.3435922077],"iteration":850,"passed_time":7.860490652,"remain,
{"learn":[0.34457772,
{"learn":[0.3430550459],"iteration":851,"passed_time":7.868564839,"remai,
{"learn":[0.344406783,
{"learn":[0.3428756535],"iteration":852,"passed_time":7.875187425,"remai,
{"learn":[0.344204983,
{"learn":[0.3425848432],"iteration":853,"passed_time":7.88009984,"remain,
{"learn":[0.34406566,
{"learn":[0.3424040383],"iteration":854,"passed_time":7.886655009,"remain,
{"learn":[0.34393361,
{"learn":[0.3420298078],"iteration":855,"passed_time":7.891277531,"remain,
{"learn":[0.34382539,
{"learn":[0.3419779709],"iteration":856,"passed_time":7.896165343,"remai,
{"learn":[0.3435912243],"iteration":857,"passed_time":7.742343111,"remaining_time":1.281366809},
{"learn":[0.3434753369],"iteration":858,"passed_time":7.747328142,"remaining_time":1.271680172},
{"learn":[0.3430778579],"iteration":859,"passed_time":7.752595866,"remaining_time":1.26205049},
{"learn":[0.3429704773],"iteration":860,"passed_time":7.758803237,"remaining_time":1.252582636},
{"learn":[0.3427494094],"iteration":861,"passed_time":7.764252774,"remaining_time":1.243001024},
{"learn":[0.342658568],"iteration":862,"passed_time":7.772003207,"remaining_time":1.233794252},
{"learn":[0.3425185072],"iteration":863,"passed_time":7.78253577,"remaining_time":1.225028779},
{"learn":[0.3421619928],"iteration":864,"passed_time":7.790484458,"remaining_time":1.215855956},
{"learn":[0.34201353,
{"learn":[0.3400546096],"iteration":865,"passed_time":7.955439324,"remain,
{"learn":[0.34177326,
{"learn":[0.3398491348],"iteration":866,"passed_time":7.965138727,"remai,
{"learn":[0.341498257,
{"learn":[0.3397941278],"iteration":867,"passed_time":7.97282729,"remain,
{"learn":[0.34122822,
{"learn":[0.3396235479],"iteration":868,"passed_time":7.980185056,"remaining_time":1.202996827},
{"learn":[0.339250952],"iteration":869,"passed_time":7.985427619,"remaining_time":1.193224817},
{"learn":[0.3390306864],"iteration":870,"passed_time":7.99286308,"remaining_time":1.183787988},
{"learn":[0.3387416969],"iteration":871,"passed_time":7.999461872,"remaining_time":1.174232935},
{"learn":[0.3386858937],"iteration":872,"passed_time":8.016512456,"remaining_time":1.166205134},
{"learn":[0.3381967579],"iteration":873,"passed_time":8.021638976,"remaining_time":1.156437656},
{"learn":[0.3380043866],"iteration":874,"passed_time":8.027218751,"remaining_time":1.146745536},
{"learn":[0.337658813],"iteration":875,"passed_time":8.032934766,"remaining_time":1.13708209},
{"learn":[0.3375378991],"iteration":876,"passed_time":8.041470023,"remaining_time":1.127823048},
{"learn":[0.3373551367],"iteration":877,"passed_time":8.04624003,"remaining_time":1.118042464},
{"learn":[0.3371027041],"iteration":878,"passed_time":8.052213733,"remaining_time":1.108438978},
{"learn":[0.3368597514],"iteration":879,"passed_time":8.058361096,"remaining_time":1.098867422},
{"learn":[0.3365509498],"iteration":880,"passed_time":8.065100538,"remaining_time":1.089383614},
{"learn":[0.3364086764],"iteration":881,"passed_time":8.069320573,"remaining_time":1.079568966},
{"learn":[0.3361322624],"iteration":882,"passed_time":8.075981572,"remaining_time":1.070090424},
{"learn":[0.3359238333],"iteration":883,"passed_time":8.081152349,"remaining_time":1.060422706},
{"learn":[0.3358017195],"iteration":884,"passed_time":8.088036664,"remaining_time":1.050987815},
{"learn":[0.3355772529],"iteration":885,"passed_time":8.093376355,"remaining_time":1.041359937},
{"learn":[0.3353693952],"iteration":886,"passed_time":8.098844938,"remaining_time":1.031758149},
{"learn":[0.3351877514],"iteration":887,"passed_time":8.10689123,"remaining_time":1.022490786},
{"learn":[0.3351243045],"iteration":888,"passed_time":8.113381726,"remaining_time":1.013031914},
{"learn":[0.335022283],"iteration":889,"passed_time":8.120384371,"remaining_time":1.003643012},
{"learn":[0.3349103909],"iteration":890,"passed_time":8.128097858,"remaining_time":0.9943464271},
{"learn":[0.33476191],"iteration":891,"passed_time":8.132046683,"remaining_time":0.9845975804},
{"learn":[0.334612327],"iteration":892,"passed_time":8.139456834,"remaining_time":0.9752764628},
{"learn":[0.3344920051],"iteration":893,"passed_time":8.144616794,"remaining_time":0.965692819},
{"learn":[0.3343394009],"iteration":894,"passed_time":8.151086697,"remaining_time":0.956272741},
{"learn":[0.3338948641],"iteration":895,"passed_time":8.155900601,"remaining_time":0.946667034},
{"learn":[0.3337914092],"iteration":896,"passed_time":8.160629246,"remaining_time":0.9370622211},
{"learn":[0.333721933],"iteration":897,"passed_time":8.167226554,"remaining_time":0.9276805217},
{"learn":[0.3336033826],"iteration":898,"passed_time":8.171237511,"remaining_time":0.9180144479},
{"learn":[0.3332772319],"iteration":899,"passed_time":8.175331697,"remaining_time":0.9083701886},
{"learn":[0.3328683792],"iteration":900,"passed_time":8.180439672,"remaining_time":0.8988496421},
{"learn":[0.3328195821],"iteration":901,"passed_time":8.185911911,"remaining_time":0.889378456},
{"learn":[0.3325158896],"iteration":902,"passed_time":8.191670519,"remaining_time":0.8799468885},
{"learn":[0.3322906249],"iteration":903,"passed_time":8.200340599,"remaining_time":0.87083263},
{"learn":[0.3322413091],"iteration":904,"passed_time":8.210445663,"remaining_time":0.8618699868},
{"learn":[0.3318770154],"iteration":905,"passed_time":8.227206735,"remaining_time":0.8535954007},
{"learn":[0.3315681821],"iteration":906,"passed_time":8.238715592,"remaining_time":0.8447635613},
{"learn":[0.3315135049],"iteration":907,"passed_time":8.247237872,"remaining_time":0.8356232205},
{"learn":[0.3313283206],"iteration":908,"passed_time":8.252835713,"remaining_time":0.826191474},
{"learn":[0.3312307455],"iteration":909,"passed_time":8.263811138,"remaining_time":0.8173000027},
{"learn":[0.3311296085],"iteration":910,"passed_time":8.279043196,"remaining_time":0.8088198073},
{"learn":[0.3309765417],"iteration":911,"passed_time":8.284485082,"remaining_time":0.7993801395},
{"learn":[0.3308359049],"iteration":912,"passed_time":8.288656729,"remaining_time":0.7898281878},
{"learn":[0.3305908203],"iteration":913,"passed_time":8.297307214,"remaining_time":0.7807094315},
{"learn":[0.330465035],"iteration":914,"passed_time":8.301074783,"remaining_time":0.7711380946},
{"learn":[0.3300179577],"iteration":915,"passed_time":8.305132,"remaining_time":0.7616059913},
{"learn":[0.3297787551],"iteration":916,"passed_time":8.317463062,"remaining_time":0.7528347156},
{"learn":[0.3296380699],"iteration":917,"passed_time":8.328659146,"remaining_time":0.7439543028},
{"learn":[0.3293195792],"iteration":918,"passed_time":8.336393913,"remaining_time":0.7347637725},
{"learn":[0.3292313242],"iteration":919,"passed_time":8.344730863,"remaining_time":0.7256287707},
{"learn":[0.328923577],"iteration":920,"passed_time":8.35098642,"remaining_time":0.7163169676},
{"learn":[0.3288036037],"iteration":921,"passed_time":8.366097556,"remaining_time":0.7077609646},
{"learn":[0.3285740224],"iteration":922,"passed_time":8.376129401,"remaining_time":0.6987670248},
{"learn":[0.3282664491],"iteration":923,"passed_time":8.381698572,"remaining_time":0.6894037787},
{"learn":[0.3281570261],"iteration":924,"passed_time":8.390006192,"remaining_time":0.6802707723},
{"learn":[0.3280920448],"iteration":925,"passed_time":8.396005075,"remaining_time":0.6709550492},
{"learn":[0.3277522869],"iteration":926,"passed_time":8.400479661,"remaining_time":0.6615264458},
{"learn":[0.3276239435],"iteration":927,"passed_time":8.414255088,"remaining_time":0.6528301362},
{"learn":[0.3273165447],"iteration":928,"passed_time":8.424097115,"remaining_time":0.6438222768},
{"learn":[0.3272473585],"iteration":929,"passed_time":8.42952842,"remaining_time":0.6344806337},
{"learn":[0.3268710894],"iteration":930,"passed_time":8.435862059,"remaining_time":0.6252142664},
{"learn":[0.326754257],"iteration":931,"passed_time":8.442039533,"remaining_time":0.6159427985},
{"learn":[0.3266713103],"iteration":932,"passed_time":8.446682954,"remaining_time":0.6065678006},
{"learn":[0.3265388566],"iteration":933,"passed_time":8.456203988,"remaining_time":0.5975476052},
{"learn":[0.3260879741],"iteration":934,"passed_time":8.461178527,"remaining_time":0.5882102719},
{"learn":[0.3258690709],"iteration":935,"passed_time":8.468639657,"remaining_time":0.5790522842},
{"learn":[0.325810315],"iteration":936,"passed_time":8.473618077,"remaining_time":0.5697309913},
{"learn":[0.3257014589],"iteration":937,"passed_time":8.478180891,"remaining_time":0.5603914875},
{"learn":[0.3252316868],"iteration":938,"passed_time":8.485456776,"remaining_time":0.5512384061},
{"learn":[0.3251976132],"iteration":939,"passed_time":8.489478452,"remaining_time":0.5418816033},
{"learn":[0.3249106521],"iteration":940,"passed_time":8.493669069,"remaining_time":0.5325467323},
{"learn":[0.3244633427],"iteration":941,"passed_time":8.500120914,"remaining_time":0.5233620096},
{"learn":[0.3240967104],"iteration":942,"passed_time":8.50543576,"remaining_time":0.5141143566},
{"learn":[0.3237974125],"iteration":943,"passed_time":8.510073494,"remaining_time":0.5048348683},
{"learn":[0.3237430169],"iteration":944,"passed_time":8.518315854,"remaining_time":0.4957749968},
{"learn":[0.3236751743],"iteration":945,"passed_time":8.524411607,"remaining_time":0.4865943201},
{"learn":[0.3233197537],"iteration":946,"passed_time":8.530124458,"remaining_time":0.4773987289},
{"learn":[0.3231132277],"iteration":947,"passed_time":8.538606244,"remaining_time":0.4683623678},
{"learn":[0.3229561992],"iteration":948,"passed_time":8.542804305,"remaining_time":0.4590969647},
{"learn":[0.3228260874],"iteration":949,"passed_time":8.549578954,"remaining_time":0.4499778397},
{"learn":[0.3227236796],"iteration":950,"passed_time":8.554066359,"remaining_time":0.4407457956},
{"learn":[0.3223256419],"iteration":951,"passed_time":8.559657971,"remaining_time":0.4315793935},
{"learn":[0.3222719705],"iteration":952,"passed_time":8.564918474,"remaining_time":0.422404164},
{"learn":[0.3218946971],"iteration":953,"passed_time":8.568590638,"remaining_time":0.4131605549},
{"learn":[0.3215742764],"iteration":954,"passed_time":8.573729607,"remaining_time":0.4039977302},
{"learn":[0.3213538725],"iteration":955,"passed_time":8.579614961,"remaining_time":0.394877676},
{"learn":[0.3210829316],"iteration":956,"passed_time":8.585369692,"remaining_time":0.3857585128},
{"learn":[0.3209878053],"iteration":957,"passed_time":8.594442249,"remaining_time":0.3767918314},
{"learn":[0.3209476312],"iteration":958,"passed_time":8.60149287,"remaining_time":0.3677384856},
{"learn":[0.3206619008],"iteration":959,"passed_time":8.609954328,"remaining_time":0.358748097},
{"learn":[0.3205906343],"iteration":960,"passed_time":8.615500275,"remaining_time":0.3496404898},
{"learn":[0.320257426],"iteration":961,"passed_time":8.620338772,"remaining_time":0.3405123424},
{"learn":[0.3201612101],"iteration":962,"passed_time":8.629022599,"remaining_time":0.3315408475},
{"learn":[0.3200810755],"iteration":963,"passed_time":8.63359413,"remaining_time":0.3224163783},
{"learn":[0.3198135091],"iteration":964,"passed_time":8.637708709,"remaining_time":0.3132847718},
{"learn":[0.3194362616],"iteration":965,"passed_time":8.643558358,"remaining_time":0.3042246213},
{"learn":[0.3191629609],"iteration":966,"passed_time":8.649399508,"remaining_time":0.2951708208},
{"learn":[0.3190372425],"iteration":967,"passed_time":8.660933065,"remaining_time":0.2863118369},
{"learn":[0.3188090378],"iteration":968,"passed_time":8.667236665,"remaining_time":0.2772800172},
{"learn":[0.3185853684],"iteration":969,"passed_time":8.677056427,"remaining_time":0.2683625699},
{"learn":[0.3181043206],"iteration":970,"passed_time":8.681633563,"remaining_time":0.2592866872},
{"learn":[0.3177556231],"iteration":971,"passed_time":8.686759154,"remaining_time":0.2502358604},
{"learn":[0.3176506944],"iteration":972,"passed_time":8.693488642,"remaining_time":0.2412376088},
{"learn":[0.3173469364],"iteration":973,"passed_time":8.698048789,"remaining_time":0.2321861073},
{"learn":[0.3171411025],"iteration":974,"passed_time":8.705972786,"remaining_time":0.2232300714},
{"learn":[0.3170079643],"iteration":975,"passed_time":8.713050729,"remaining_time":0.2142553458},
{"learn":[0.3168333796],"iteration":976,"passed_time":8.722869244,"remaining_time":0.2053490201},
{"learn":[0.316435961],"iteration":977,"passed_time":8.729221205,"remaining_time":0.1963628492},
{"learn":[0.3162049217],"iteration":978,"passed_time":8.733366544,"remaining_time":0.1873347267},
{"learn":[0.3161397944],"iteration":979,"passed_time":8.739473914,"remaining_time":0.1783566105},
{"learn":[0.3159156756],"iteration":980,"passed_time":8.744727701,"remaining_time":0.1693678148},
{"learn":[0.3157514256],"iteration":981,"passed_time":8.748704533,"remaining_time":0.1603632195},
{"learn":[0.31568073],"iteration":982,"passed_time":8.754201171,"remaining_time":0.1513951372},
{"learn":[0.3154535899],"iteration":983,"passed_time":8.759221343,"remaining_time":0.1424263633},
{"learn":[0.3153771561],"iteration":984,"passed_time":8.764013258,"remaining_time":0.1334621308},
{"learn":[0.315172194],"iteration":985,"passed_time":8.770773857,"remaining_time":0.1245343144},
{"learn":[0.3149605062],"iteration":986,"passed_time":8.776325374,"remaining_time":0.1155949644},
{"learn":[0.3146972375],"iteration":987,"passed_time":8.7795358,"remaining_time":0.1066340381},
{"learn":[0.314520582],"iteration":988,"passed_time":8.786912122,"remaining_time":0.09773107517},
{"learn":[0.3143682277],"iteration":989,"passed_time":8.79070895,"remaining_time":0.0887950399},
{"learn":[0.3142621931],"iteration":990,"passed_time":8.794912884,"remaining_time":0.07987307362},
{"learn":[0.3140937484],"iteration":991,"passed_time":8.802015424,"remaining_time":0.07098399536},
{"learn":[0.3140154551],"iteration":992,"passed_time":8.807850846,"remaining_time":0.06208958301},
{"learn":[0.3138795298],"iteration":993,"passed_time":8.816336823,"remaining_time":0.05321732489},
{"learn":[0.3137568104],"iteration":994,"passed_time":8.823623387,"remaining_time":0.04433981602},
{"learn":[0.3135739872],"iteration":995,"passed_time":8.833040785,"remaining_time":0.03547405938},
{"learn":[0.3132900781],"iteration":996,"passed_time":8.839587139,"remaining_time":0.02659855709},
{"learn":[0.3132384786],"iteration":997,"passed_time":8.845922491,"remaining_time":0.01772729958},
{"learn":[0.3131714407],"iteration":998,"passed_time":8.85172553,"remaining_time":0.008860586116},
{"learn":[0.3129573702],"iteration":999,"passed_time":8.856659655,"remaining_time":0}
]}